Workbook

Sheet ALLEGATO 1 CONDOMINI
N1: Agente di Riferimento (codice, nome e cognome): 340
A6: ALLEGATO 1 - Tabella riepilogativa punti di fornitura DI GAS NATURALE
E15: Indirizzo di fornitura
A16: Nr. | B16: Ragione Sociale | D16: P.IVA / Codice Fiscale | E16: Indirizzo (toponimo, nome via, civico) | H16: Cap | I16: Città | J16: Prov | K16: IBAN | L16: PDR | M16: Attuale Fornitore | N16: Matricola Contatore | O16: REMI | P16: Cons.Pres. Annuo (smc)
A17: 1 | B17: COND. | H17: =VLOOKUP(I17,'Zone Istat'!A:E,5,FALSE) -> #N/A | J17: =VLOOKUP(I17,'Zone Istat'!A:D,4,FALSE) -> #N/A
A18: 2 | B18: COND. | H18: =VLOOKUP(I18,'Zone Istat'!A:E,5,FALSE) -> #N/A | J18: =VLOOKUP(I18,'Zone Istat'!A:D,4,FALSE) -> #N/A
A19: 3 | B19: COND. | H19: =VLOOKUP(I19,'Zone Istat'!A:E,5,FALSE) -> #N/A | J19: =VLOOKUP(I19,'Zone Istat'!A:D,4,FALSE) -> #N/A
A20: 4 | B20: COND. | H20: =VLOOKUP(I20,'Zone Istat'!A:E,5,FALSE) -> #N/A | J20: =VLOOKUP(I20,'Zone Istat'!A:D,4,FALSE) -> #N/A
A21: 5 | B21: COND. | H21: =VLOOKUP(I21,'Zone Istat'!A:E,5,FALSE) -> #N/A | J21: =VLOOKUP(I21,'Zone Istat'!A:D,4,FALSE) -> #N/A
A22: 6 | B22: COND. | H22: =VLOOKUP(I22,'Zone Istat'!A:E,5,FALSE) -> #N/A | J22: =VLOOKUP(I22,'Zone Istat'!A:D,4,FALSE) -> #N/A
A23: 7 | B23: COND. | H23: =VLOOKUP(I23,'Zone Istat'!A:E,5,FALSE) -> #N/A | J23: =VLOOKUP(I23,'Zone Istat'!A:D,4,FALSE) -> #N/A
A24: 8 | B24: COND. | H24: =VLOOKUP(I24,'Zone Istat'!A:E,5,FALSE) -> #N/A | J24: =VLOOKUP(I24,'Zone Istat'!A:D,4,FALSE) -> #N/A
A25: 9 | B25: COND. | H25: =VLOOKUP(I25,'Zone Istat'!A:E,5,FALSE) -> #N/A | J25: =VLOOKUP(I25,'Zone Istat'!A:D,4,FALSE) -> #N/A
A26: 10 | B26: COND. | H26: =VLOOKUP(I26,'Zone Istat'!A:E,5,FALSE) -> #N/A | J26: =VLOOKUP(I26,'Zone Istat'!A:D,4,FALSE) -> #N/A
A27: 11 | B27: COND. | H27: =VLOOKUP(I27,'Zone Istat'!A:E,5,FALSE) -> #N/A | J27: =VLOOKUP(I27,'Zone Istat'!A:D,4,FALSE) -> #N/A
A28: 12 | B28: COND. | H28: =VLOOKUP(I28,'Zone Istat'!A:E,5,FALSE) -> #N/A | J28: =VLOOKUP(I28,'Zone Istat'!A:D,4,FALSE) -> #N/A
... A36: 20 | B36: COND. | H36: =VLOOKUP(I36,'Zone Istat'!A:E,5,FALSE) -> #N/A | J36: =VLOOKUP(I36,'Zone Istat'!A:D,4,FALSE) -> #N/A
A40: Luogo: | M40: Firma ___________________________________________________________
Q46: Agente di Riferimento (codice, nome e cognome):
A48: ALLEGATO 1 - Tabella riepilogativa punti di fornitura di ENERGIA ELETTRICA
E54: Indirizzo di fornitura
A55: Nr. | B55: Ragione Sociale del Condominio | D55: P.IVA / Codice Fiscale | E55: Indirizzo (toponimo, nome via, civico) | H55: Cap | I55: Città | J55: Prov | K55: IBAN | L55: POD | M55: Distibutore | N55: Attuale Fornitore | O55: Cons.Pres. Annuo (KWh) | P55: IVA | Q55: Potenza Disponibile | R55: Potenza Impegnata | S55: Tensione V
A56: 1 | B56: COND. | H56: =VLOOKUP(I56,'Zone Istat'!A:E,5,FALSE) -> #N/A | J56: =VLOOKUP(I56,'Zone Istat'!A:D,4,FALSE) -> #N/A
A57: 2 | B57: COND. | H57: =VLOOKUP(I57,'Zone Istat'!A:E,5,FALSE) -> #N/A | J57: =VLOOKUP(I57,'Zone Istat'!A:D,4,FALSE) -> #N/A
A58: 3 | B58: COND. | H58: =VLOOKUP(I58,'Zone Istat'!A:E,5,FALSE) -> #N/A | J58: =VLOOKUP(I58,'Zone Istat'!A:D,4,FALSE) -> #N/A
A59: 4 | B59: COND. | H59: =VLOOKUP(I59,'Zone Istat'!A:E,5,FALSE) -> #N/A | J59: =VLOOKUP(I59,'Zone Istat'!A:D,4,FALSE) -> #N/A
A60: 5 | B60: COND. | H60: =VLOOKUP(I60,'Zone Istat'!A:E,5,FALSE) -> #N/A | J60: =VLOOKUP(I60,'Zone Istat'!A:D,4,FALSE) -> #N/A
A61: 6 | B61: COND. | H61: =VLOOKUP(I61,'Zone Istat'!A:E,5,FALSE) -> #N/A | J61: =VLOOKUP(I61,'Zone Istat'!A:D,4,FALSE) -> #N/A
A62: 7 | B62: COND. | H62: =VLOOKUP(I62,'Zone Istat'!A:E,5,FALSE) -> #N/A | J62: =VLOOKUP(I62,'Zone Istat'!A:D,4,FALSE) -> #N/A
A63: 8 | B63: COND. | H63: =VLOOKUP(I63,'Zone Istat'!A:E,5,FALSE) -> #N/A | J63: =VLOOKUP(I63,'Zone Istat'!A:D,4,FALSE) -> #N/A
A64: 9 | B64: COND. | H64: =VLOOKUP(I64,'Zone Istat'!A:E,5,FALSE) -> #N/A | J64: =VLOOKUP(I64,'Zone Istat'!A:D,4,FALSE) -> #N/A
A65: 10 | B65: COND. | H65: =VLOOKUP(I65,'Zone Istat'!A:E,5,FALSE) -> #N/A | J65: =VLOOKUP(I65,'Zone Istat'!A:D,4,FALSE) -> #N/A
A66: 11 | B66: COND. | H66: =VLOOKUP(I66,'Zone Istat'!A:E,5,FALSE) -> #N/A | J66: =VLOOKUP(I66,'Zone Istat'!A:D,4,FALSE) -> #N/A
A67: 12 | B67: COND. | H67: =VLOOKUP(I67,'Zone Istat'!A:E,5,FALSE) -> #N/A | J67: =VLOOKUP(I67,'Zone Istat'!A:D,4,FALSE) -> #N/A
... A75: 20 | B75: COND. | H75: =VLOOKUP(I75,'Zone Istat'!A:E,5,FALSE) -> #N/A | J75: =VLOOKUP(I75,'Zone Istat'!A:D,4,FALSE) -> #N/A
A77: Nota 1: Si richiede applicazione dell'iva al 10% e si allega documento attestante l'uso esclusivamente residenziale del POD indicato (autocertificazione).
A78: In caso di mancata ricezione o compilazione della predetta autocertificazione, il Cliente non avrà diritto all’agevolazione; il ritardato ricevimento non comporterà l’applicazione retroattiva.
A81: Luogo _________________________________________________ Data _______________________________ | N81: Firma ___________________________________________________________

Sheet Template G
A1: Cliente - Num | B1: Cliente - Nome | C1: Cliente - Cognome | D1: Cliente - Ragione Sociale | E1: Cliente - Partita IVA | F1: Cliente - Codice Fiscale | G1: Cliente - Telefono | H1: Cliente - Fax | I1: Cliente - E-Mail | J1: Cliente - E-Mail PEC | K1: Cliente - Cat. Reg. Business | L1: Cliente - Cat. Reg. Business IVA | M1: Cliente - Cat. Reg. Cliente | N1: Cliente - Codice Agente | O1: Cliente - Nome Agente | P1: Indirizzo Cliente - Codice Zona (ISTAT) | Q1: Indirizzo Cliente - Descrizione Comune | R1: Indirizzo Cliente - CAP | S1: Indirizzo Cliente - Provincia | T1: Indirizzo Cliente - Tipo Via | U1: Indirizzo Cliente - Nome Via | V1: Indirizzo Cliente - Numero Civico | W1: Indirizzo Cliente - Estensione Civico | X1: Indirizzo Cliente - Scala | Y1: Indirizzo Cliente - Piano | Z1: Indirizzo Cliente - Interno | AA1: Pagamenti - Codice Metodo Di Pagamento | AB1: Pagamenti - Codice Condizioni Di Pagamento | AC1: Cliente - Codice Temini di Sollecito | AD1: Pagamenti - Esente Mora | AE1: Pagamenti - Tipo Configurazione Mora | AF1: Rappresentante Legale - Nome | AG1: Rappresentante Legale - Codice Fiscale | AH1: Utenza - Nome | AI1: Utenza - Cognome | AJ1: Utenza - Ragione Sociale | AK1: Utenza - Codice Raggruppamento | AL1: Cat reg business | AM1: cat reg business iva | AN1: Utenza - Tipo Utenza | AO1: Utenza - Classe Utenza | AP1: Utenza - Categoria Utenza | AQ1: codice agente | AR1: nome agente | AS1: Utenza - Tipo Mercato | AT1: Utenza - Tipo Mercato Di Provenienza | AU1: Utenza - Provenienza Prenotazione | AV1: Utenza - Categoria Uso | AW1: Utenza - Classe Prelievo | AX1: codice venditore | AY1: Utenza - Codice Distributore | AZ1: Utenza - Codice Fornitore | BA1: Utenza - Data Apertura | BB1: Utenza - Frequenza Fatturazione | BC1: Utenza - Frequenza Lettura | BD1: Utenza - Consumo Annuo Presunto | BE1: Utenza - Cumulo Consumi Iniziale | BF1: Utenza - Tipologia Offerta | BG1: Utenza - Codice Offerta | BH1: Utenza - Data Inizio Offerta | BI1: Utenza - Data Fine Offerta | BJ1: Utenza - Tipo Invio Fatture | BK1: utenza metodo di pagamento | BL1: utenza termini di pagamento | BM1: Utenza - Tipo Configurazione Mora | BN1: PDR - Nr. | BO1: PDR - Cabina Remi | BP1: PDR - Coefficiente C | BQ1: Indirizzo PDR - Codice Zona (ISTAT) | BR1: Indirizzo PDR - Descrizione Comune | BS1: Indirizzo PDR - CAP | BT1: Indirizzo PDR - Provincia | BU1: Indirizzo PDR - Tipo Via | BV1: Indirizzo PDR - Nome Via | BW1: Indirizzo PDR - Numero Civico | BX1: Indirizzo PDR - Estensione Civico | BY1: Indirizzo PDR - Scala | BZ1: Indirizzo PDR - Piano | CA1: Indirizzo PDR - Interno | CB1: Misuratore - Matricola | CC1: Misuratore - Tipo | CD1: Misuratore - Tipologia | CE1: Misuratore - Data Apertura | CF1: Misuratore - Valore Apertura | CG1: Misuratore - Nr. Cifre | CH1: Contratto - Nr, | CI1: Contratto - Data Apertura | CJ1: Contratto - Data Scadenza | CK1: Contratto - Prezzo Di Partenza | CL1: Contratto - Valore PCS | CM1: Contratto - Indice Energetico | CN1: Contratto - Moltiplicatore | CO1: Contratto - Codice Paniere | CP1: Contratto - Capacità Giornaliera | CQ1: Indirizzo Spedizione - Tipo | CR1: Indirizzo Spedizione - Nome | CS1: Indirizzo Spedizione - E-Mail | CT1: Indirizzo Spedizione - Codice Zona (ISTAT) | CU1: Indirizzo Spedizione - Descrizione Comune | CV1: Indirizzo Spedizione - CAP | CW1: Indirizzo Spedizione - Provincia | CX1: Indirizzo Spedizione - Tipo Via | CY1: Indirizzo Spedizione - Nome Via | CZ1: Indirizzo Spedizione - Numero Civico | DA1: Indirizzo Spedizione - Estensione Civico | DB1: Indirizzo Spedizione - Scala | DC1: Indirizzo Spedizione - Piano | DD1: Indirizzo Spedizione - Interno | DE1: RID - Stato | DF1: RID - Codice Domiciliazione | DG1: RID - Nome Intestatario | DH1: RID - CF Intestatario | DI1: RID - IBAN | DJ1: RID - Codice SIA | DK1: RID - Data Inizio Domiciliazione | DL1: RID - Data Inizio Garanzie | DM1: Lettera Intento - Nr, | DN1: Lettera Intento - Decorrenza Da | DO1: Lettera Intento - Decorrenza A | DP1: Dati Catastali - Codice Comune Catastale | DQ1: Dati Catastali - Foglio | DR1: Dati Catastali - Tavola | DS1: Dati Catastali - Particella | DT1: Dati Catastali - Subalterno | DU1: Cod. Stampa | DV1: Correttore - Nr. | DW1: Correttore - Tipo | DX1: Correttore - Data Apertura | DY1: Correttore - Valore Apertura | DZ1: Correttore - Nr. Cifre | EA1: Utenza - Nome Controparte | EB1: Utenza - Partita IVA Controparte | EC1: Utenza - Cod. Fiscale Controparte | ED1: Cod. Ex Venditore | EE1: Contratto - Data firma contratto | EF1: Cliente - Tipo Telefono | EG1: Cliente - Nr. Cliente Esterno | EH1: Indirizzo Cliente - Codice Nazione | EI1: Utenza - Cod. Tipo Servizio | EJ1: Utenza - Mercato di Appartenenza | EK1: Utenza - Metodo di Calcolo Acconti | EL1: Utenza - Codice Termini di Sollecito | EM1: Opificio | EN1: Utenza - Esente Mora | EO1: Utenza - Campo Personalizzato 1 | EP1: Punto di Riconsegna - Fornitura Diretta | EQ1: POD - Data Prima Apertura | ER1: Punto di Riconsegna - Relazione Società-Punto di Riconsegna | ES1: Misuratore - Tipo Lettura Aperura | ET1: Corrispondenza - Codice Nazione | EU1: Domiciliazione - Partita IVA Intestatario | EV1: Domiciliazione - Tipo Partner | EW1: Utenza - Nr. Amministratore | EX1: Amministratore - Nome | EY1: Amministratore - Cognome | EZ1: Amministratore - Ragione Sociale | FA1: Amministratore - Codice Fiscale | FB1: Amministratore - Partita IVA | FC1: Amministratore - Cod. Zona (ISTAT) | FD1: Amministratore - Città | FE1: Amministratore - CAP | FF1: Amministratore - Cod. Provincia | FG1: Amministratore - Tipo Via | FH1: Amministratore - Nome Via | FI1: Amministratore - Civico | FJ1: Amministratore - Estensione | FK1: Amministratore - Scala | FL1: Amministratore - Piano | FM1: Amministratore - Interno | FN1: Amministratore - Telefono | FO1: Amministratore - E-Mail | FP1: Utenza - Nr. | FQ1: Utenza - Tipo Contratto | FR1: Utenza - Data Switch Vendita | FS1: Utenza - Fabbisogno KWH | FT1: Utenza - Cod. Settore Merceologico | FU1: Utenza - Campo Personalizzato 2 | FV1: Utenza - Campo Personalizzato 3 | FW1: Utenza - Nr. Contratto Esterno | FX1: Utenza - Cod. Accisa Personale | FY1: Contratto - Unitario Mensile Termine fisso | FZ1: Contratto - Spread | GA1: Contratto - Importo Costante | GB1: Contratto - Tipo Importo Costante | GC1: Dichiarazione Intento - Anno Dichiarazione | GD1: Dichiarazione Intento - Plafond Iniziale | GE1: Dichiarazione Intento - Data Presentazione Dichiarazione | GF1: Dichiarazione Intento - Nr. Attribuito dal Dichiarante | GG1: Dichiarazione Intento - Anno Attribuito dal Dichiarante | GH1: Dichiarazione Intento - Nr. Attribuito dal Fornitore | GI1: Dichiarazione Intento - Anno Attribuito dal Fornitore | GJ1: Consenso Future iniziative promozionali curate dalla società di vendita | GK1: Consenso Future iniziative promozionali curate da altre imprese del settore energia e servizi | GL1: Analisi/ricerche di mercato effettuate direttamente dalla società di vendita tramite società terze | GM1: Codice OU | GN1: Shipper | GO1: Cliente - Autorizzazione Invio SMS | GP1: Cliente - Codice Lingua | GQ1: Utenza - Layout Stampa | GR1: Utenza - Nome controparte | GS1: Utenza - Cognome controparte | GT1: Nr. contratto PA | GU1: Codice CIG | GV1: Codice CUP | GW1: Contratto - Luogo Firma Contratto
D2: =_xlfn.CONCAT('ALLEGATO 1 CONDOMINI'!B17,'ALLEGATO 1 CONDOMINI'!C17) -> COND. | F2: ='ALLEGATO 1 CONDOMINI'!D17 -> 0 | K2: CLIENTI | L2: 22 | M2: CLI-RD | P2: =VLOOKUP(Q2,'Zone Istat'!A:E,2,FALSE) -> #N/A | Q2: ='ALLEGATO 1 CONDOMINI'!I17 -> 0 | R2: =VLOOKUP(Q2,'Zone Istat'!A:E,5,FALSE) -> #N/A | S2: =VLOOKUP(Q2,'Zone Istat'!A:E,4,FALSE) -> #N/A | T2: ='ALLEGATO 1 CONDOMINI'!E17 -> 0 | U2: ='ALLEGATO 1 CONDOMINI'!F17 -> 0 | V2: ='ALLEGATO 1 CONDOMINI'!G17 -> 0 | AA2: RID | AB2: 30DF | AC2: COND | AD2: NO | AE2: ND | AJ2: =D2 -> COND. | AL2: CLIENTI | AM2: 22 | AN2: 5 | AO2: 2 | AP2: 9904 | AS2: COND.USO DOM LIBERO | AU2: SWITCH | AV2: C1 | AW2: 1 | AX2: 00001 | AY2: =MID(BN2,1,4) -> 0 | BB2: 12 | BC2: =IF(BD2<=4999,"04","12") -> 04 | BD2: ='ALLEGATO 1 CONDOMINI'!P17 -> 0 | BK2: RID | BL2: 30DF | BM2: ND | BN2: ='ALLEGATO 1 CONDOMINI'!L17 -> 0 | BO2: ='ALLEGATO 1 CONDOMINI'!O17 -> 0 | BQ2: =P2 -> #N/A | BR2: =Q2 -> 0 | BS2: =R2 -> #N/A | BT2: =S2 -> #N/A | BU2: =T2 -> 0 | BV2: =U2 -> 0 | BW2: =V2 -> 0 | CB2: ='ALLEGATO 1 CONDOMINI'!N17 -> 0 | CQ2: AMMINISTRATORE | DE2: ATTIVA | DG2: =AF2 -> 0 | DH2: =AG2 -> 0 | DI2: ='ALLEGATO 1 CONDOMINI'!K17 -> 0 | DJ2: B5746 | ED2: =VLOOKUP('ALLEGATO 1 CONDOMINI'!M17,Venditori!B:E,4,FALSE) -> #N/A | EI2: G | EK2: profilo di prelievo | EL2: COND | EO2: =MID(D2,1,20) -> COND. | ER2: Controparte Commerciale & UDD | EV2: Core | FT2: 97.00.02 | GJ2: NO | GK2: NO | GL2: NO | GN2: 28 | GO2: NO | GP2: ITA
D3: =_xlfn.CONCAT('ALLEGATO 1 CONDOMINI'!B18,'ALLEGATO 1 CONDOMINI'!C18) -> COND. | F3: ='ALLEGATO 1 CONDOMINI'!D18 -> 0 | K3: CLIENTI | L3: 22 | M3: CLI-RD | P3: =VLOOKUP(Q3,'Zone Istat'!A:E,2,FALSE) -> #N/A | Q3: ='ALLEGATO 1 CONDOMINI'!I18 -> 0 | R3: =VLOOKUP(Q3,'Zone Istat'!A:E,5,FALSE) -> #N/A | S3: =VLOOKUP(Q3,'Zone Istat'!A:E,4,FALSE) -> #N/A | T3: ='ALLEGATO 1 CONDOMINI'!E18 -> 0 | U3: ='ALLEGATO 1 CONDOMINI'!F18 -> 0 | V3: ='ALLEGATO 1 CONDOMINI'!G18 -> 0 | AA3: RID | AB3: 30DF | AC3: COND | AD3: NO | AE3: ND | AJ3: =D3 -> COND. | AL3: CLIENTI | AM3: 22 | AN3: 5 | AO3: 2 | AP3: 9904 | AS3: COND.USO DOM LIBERO | AU3: SWITCH | AV3: C1 | AW3: 1 | AX3: 00001 | AY3: =MID(BN3,1,4) -> 0 | BB3: 12 | BC3: =IF(BD3<=4999,"04","12") -> 04 | BD3: ='ALLEGATO 1 CONDOMINI'!P18 -> 0 | BK3: RID | BL3: 30DF | BM3: ND | BN3: ='ALLEGATO 1 CONDOMINI'!L18 -> 0 | BO3: ='ALLEGATO 1 CONDOMINI'!O18 -> 0 | BQ3: =P3 -> #N/A | BR3: =Q3 -> 0 | BS3: =R3 -> #N/A | BT3: =S3 -> #N/A | BU3: =T3 -> 0 | BV3: =U3 -> 0 | BW3: =V3 -> 0 | CB3: ='ALLEGATO 1 CONDOMINI'!N18 -> 0 | CQ3: AMMINISTRATORE | DE3: ATTIVA | DG3: =AF3 -> 0 | DH3: =AG3 -> 0 | DI3: ='ALLEGATO 1 CONDOMINI'!K18 -> 0 | DJ3: B5746 | ED3: =VLOOKUP('ALLEGATO 1 CONDOMINI'!M18,Venditori!B:E,4,FALSE) -> #N/A | EI3: G | EK3: profilo di prelievo | EL3: COND | EO3: =MID(D3,1,20) -> COND. | ER3: Controparte Commerciale & UDD | EV3: Core | FT3: 97.00.02 | GJ3: NO | GK3: NO | GL3: NO | GN3: 28 | GO3: NO | GP3: ITA
D4: =_xlfn.CONCAT('ALLEGATO 1 CONDOMINI'!B19,'ALLEGATO 1 CONDOMINI'!C19) -> COND. | F4: ='ALLEGATO 1 CONDOMINI'!D19 -> 0 | K4: CLIENTI | L4: 22 | M4: CLI-RD | P4: =VLOOKUP(Q4,'Zone Istat'!A:E,2,FALSE) -> #N/A | Q4: ='ALLEGATO 1 CONDOMINI'!I19 -> 0 | R4: =VLOOKUP(Q4,'Zone Istat'!A:E,5,FALSE) -> #N/A | S4: =VLOOKUP(Q4,'Zone Istat'!A:E,4,FALSE) -> #N/A | T4: ='ALLEGATO 1 CONDOMINI'!E19 -> 0 | U4: ='ALLEGATO 1 CONDOMINI'!F19 -> 0 | V4: ='ALLEGATO 1 CONDOMINI'!G19 -> 0 | AA4: RID | AB4: 30DF | AC4: COND | AD4: NO | AE4: ND | AJ4: =D4 -> COND. | AL4: CLIENTI | AM4: 22 | AN4: 5 | AO4: 2 | AP4: 9904 | AS4: COND.USO DOM LIBERO | AU4: SWITCH | AV4: C1 | AW4: 1 | AX4: 00001 | AY4: =MID(BN4,1,4) -> 0 | BB4: 12 | BC4: =IF(BD4<=4999,"04","12") -> 04 | BD4: ='ALLEGATO 1 CONDOMINI'!P19 -> 0 | BK4: RID | BL4: 30DF | BM4: ND | BN4: ='ALLEGATO 1 CONDOMINI'!L19 -> 0 | BO4: ='ALLEGATO 1 CONDOMINI'!O19 -> 0 | BQ4: =P4 -> #N/A | BR4: =Q4 -> 0 | BS4: =R4 -> #N/A | BT4: =S4 -> #N/A | BU4: =T4 -> 0 | BV4: =U4 -> 0 | BW4: =V4 -> 0 | CB4: ='ALLEGATO 1 CONDOMINI'!N19 -> 0 | CQ4: AMMINISTRATORE | DE4: ATTIVA | DG4: =AF4 -> 0 | DH4: =AG4 -> 0 | DI4: ='ALLEGATO 1 CONDOMINI'!K19 -> 0 | DJ4: B5746 | ED4: =VLOOKUP('ALLEGATO 1 CONDOMINI'!M19,Venditori!B:E,4,FALSE) -> #N/A | EI4: G | EK4: profilo di prelievo | EL4: COND | EO4: =MID(D4,1,20) -> COND. | ER4: Controparte Commerciale & UDD | EV4: Core | FT4: 97.00.02 | GJ4: NO | GK4: NO | GL4: NO | GN4: 28 | GO4: NO | GP4: ITA
D5: =_xlfn.CONCAT('ALLEGATO 1 CONDOMINI'!B20,'ALLEGATO 1 CONDOMINI'!C20) -> COND. | F5: ='ALLEGATO 1 CONDOMINI'!D20 -> 0 | K5: CLIENTI | L5: 22 | M5: CLI-RD | P5: =VLOOKUP(Q5,'Zone Istat'!A:E,2,FALSE) -> #N/A | Q5: ='ALLEGATO 1 CONDOMINI'!I20 -> 0 | R5: =VLOOKUP(Q5,'Zone Istat'!A:E,5,FALSE) -> #N/A | S5: =VLOOKUP(Q5,'Zone Istat'!A:E,4,FALSE) -> #N/A | T5: ='ALLEGATO 1 CONDOMINI'!E20 -> 0 | U5: ='ALLEGATO 1 CONDOMINI'!F20 -> 0 | V5: ='ALLEGATO 1 CONDOMINI'!G20 -> 0 | AA5: RID | AB5: 30DF | AC5: COND | AD5: NO | AE5: ND | AJ5: =D5 -> COND. | AL5: CLIENTI | AM5: 22 | AN5: 5 | AO5: 2 | AP5: 9904 | AS5: COND.USO DOM LIBERO | AU5: SWITCH | AV5: C1 | AW5: 1 | AX5: 00001 | AY5: =MID(BN5,1,4) -> 0 | BB5: 12 | BC5: =IF(BD5<=4999,"04","12") -> 04 | BD5: ='ALLEGATO 1 CONDOMINI'!P20 -> 0 | BK5: RID | BL5: 30DF | BM5: ND | BN5: ='ALLEGATO 1 CONDOMINI'!L20 -> 0 | BO5: ='ALLEGATO 1 CONDOMINI'!O20 -> 0 | BQ5: =P5 -> #N/A | BR5: =Q5 -> 0 | BS5: =R5 -> #N/A | BT5: =S5 -> #N/A | BU5: =T5 -> 0 | BV5: =U5 -> 0 | BW5: =V5 -> 0 | CB5: ='ALLEGATO 1 CONDOMINI'!N20 -> 0 | CQ5: AMMINISTRATORE | DE5: ATTIVA | DG5: =AF5 -> 0 | DH5: =AG5 -> 0 | DI5: ='ALLEGATO 1 CONDOMINI'!K20 -> 0 | DJ5: B5746 | ED5: =VLOOKUP('ALLEGATO 1 CONDOMINI'!M20,Venditori!B:E,4,FALSE) -> #N/A | EI5: G | EK5: profilo di prelievo | EL5: COND | EO5: =MID(D5,1,20) -> COND. | ER5: Controparte Commerciale & UDD | EV5: Core | FT5: 97.00.02 | GJ5: NO | GK5: NO | GL5: NO | GN5: 28 | GO5: NO | GP5: ITA
D6: =_xlfn.CONCAT('ALLEGATO 1 CONDOMINI'!B21,'ALLEGATO 1 CONDOMINI'!C21) -> COND. | F6: ='ALLEGATO 1 CONDOMINI'!D21 -> 0 | K6: CLIENTI | L6: 22 | M6: CLI-RD | P6: =VLOOKUP(Q6,'Zone Istat'!A:E,2,FALSE) -> #N/A | Q6: ='ALLEGATO 1 CONDOMINI'!I21 -> 0 | R6: =VLOOKUP(Q6,'[1]Zone Istat'!A:E,5,FALSE) -> #N/A | S6: =VLOOKUP(Q6,'Zone Istat'!A:E,4,FALSE) -> #N/A | T6: ='ALLEGATO 1 CONDOMINI'!E21 -> 0 | U6: ='ALLEGATO 1 CONDOMINI'!F21 -> 0 | V6: ='ALLEGATO 1 CONDOMINI'!G21 -> 0 | AA6: RID | AB6: 30DF | AC6: COND | AD6: NO | AE6: ND | AJ6: =D6 -> COND. | AL6: CLIENTI | AM6: 22 | AN6: 5 | AO6: 2 | AP6: 9904 | AS6: COND.USO DOM LIBERO | AU6: SWITCH | AV6: C1 | AW6: 1 | AX6: 00001 | AY6: =MID(BN6,1,4) -> 0 | BB6: 12 | BC6: =IF(BD6<=4999,"04","12") -> 04 | BD6: ='ALLEGATO 1 CONDOMINI'!P21 -> 0 | BK6: RID | BL6: 30DF | BM6: ND | BN6: ='ALLEGATO 1 CONDOMINI'!L21 -> 0 | BO6: ='ALLEGATO 1 CONDOMINI'!O21 -> 0 | BQ6: =P6 -> #N/A | BR6: =Q6 -> 0 | BS6: =R6 -> #N/A | BT6: =S6 -> #N/A | BU6: =T6 -> 0 | BV6: =U6 -> 0 | BW6: =V6 -> 0 | CB6: ='ALLEGATO 1 CONDOMINI'!N21 -> 0 | CQ6: AMMINISTRATORE | DE6: ATTIVA | DG6: =AF6 -> 0 | DH6: =AG6 -> 0 | DI6: ='ALLEGATO 1 CONDOMINI'!K21 -> 0 | DJ6: B5746 | ED6: =VLOOKUP('ALLEGATO 1 CONDOMINI'!M21,Venditori!B:E,4,FALSE) -> #N/A | EI6: G | EK6: profilo di prelievo | EL6: COND | EO6: =MID(D6,1,20) -> COND. | ER6: Controparte Commerciale & UDD | EV6: Core | FT6: 97.00.02 | GJ6: NO | GK6: NO | GL6: NO | GN6: 28 | GO6: NO | GP6: ITA
D7: =_xlfn.CONCAT('ALLEGATO 1 CONDOMINI'!B22,'ALLEGATO 1 CONDOMINI'!C22) -> COND. | F7: ='ALLEGATO 1 CONDOMINI'!D22 -> 0 | K7: CLIENTI | L7: 22 | M7: CLI-RD | P7: =VLOOKUP(Q7,'Zone Istat'!A:E,2,FALSE) -> #N/A | Q7: ='ALLEGATO 1 CONDOMINI'!I22 -> 0 | R7: =VLOOKUP(Q7,'[1]Zone Istat'!A:E,5,FALSE) -> #N/A | S7: =VLOOKUP(Q7,'Zone Istat'!A:E,4,FALSE) -> #N/A | T7: ='ALLEGATO 1 CONDOMINI'!E22 -> 0 | U7: ='ALLEGATO 1 CONDOMINI'!F22 -> 0 | V7: ='ALLEGATO 1 CONDOMINI'!G22 -> 0 | AA7: RID | AB7: 30DF | AC7: COND | AD7: NO | AE7: ND | AJ7: =D7 -> COND. | AL7: CLIENTI | AM7: 22 | AN7: 5 | AO7: 2 | AP7: 9904 | AS7: COND.USO DOM LIBERO | AU7: SWITCH | AV7: C1 | AW7: 1 | AX7: 00001 | AY7: =MID(BN7,1,4) -> 0 | BB7: 12 | BC7: =IF(BD7<=4999,"04","12") -> 04 | BD7: ='ALLEGATO 1 CONDOMINI'!P22 -> 0 | BK7: RID | BL7: 30DF | BM7: ND | BN7: ='ALLEGATO 1 CONDOMINI'!L22 -> 0 | BO7: ='ALLEGATO 1 CONDOMINI'!O22 -> 0 | BQ7: =P7 -> #N/A | BR7: =Q7 -> 0 | BS7: =R7 -> #N/A | BT7: =S7 -> #N/A | BU7: =T7 -> 0 | BV7: =U7 -> 0 | BW7: =V7 -> 0 | CB7: ='ALLEGATO 1 CONDOMINI'!N22 -> 0 | CQ7: AMMINISTRATORE | DE7: ATTIVA | DG7: =AF7 -> 0 | DH7: =AG7 -> 0 | DI7: ='ALLEGATO 1 CONDOMINI'!K22 -> 0 | DJ7: B5746 | ED7: =VLOOKUP('ALLEGATO 1 CONDOMINI'!M22,Venditori!B:E,4,FALSE) -> #N/A | EI7: G | EK7: profilo di prelievo | EL7: COND | EO7: =MID(D7,1,20) -> COND. | ER7: Controparte Commerciale & UDD | EV7: Core | FT7: 97.00.02 | GJ7: NO | GK7: NO | GL7: NO | GN7: 28 | GO7: NO | GP7: ITA
D8: =_xlfn.CONCAT('ALLEGATO 1 CONDOMINI'!B23,'ALLEGATO 1 CONDOMINI'!C23) -> COND. | F8: ='ALLEGATO 1 CONDOMINI'!D23 -> 0 | K8: CLIENTI | L8: 22 | M8: CLI-RD | P8: =VLOOKUP(Q8,'Zone Istat'!A:E,2,FALSE) -> #N/A | Q8: ='ALLEGATO 1 CONDOMINI'!I23 -> 0 | R8: =VLOOKUP(Q8,'[1]Zone Istat'!A:E,5,FALSE) -> #N/A | S8: =VLOOKUP(Q8,'Zone Istat'!A:E,4,FALSE) -> #N/A | T8: ='ALLEGATO 1 CONDOMINI'!E23 -> 0 | U8: ='ALLEGATO 1 CONDOMINI'!F23 -> 0 | V8: ='ALLEGATO 1 CONDOMINI'!G23 -> 0 | AA8: RID | AB8: 30DF | AC8: COND | AD8: NO | AE8: ND | AJ8: =D8 -> COND. | AL8: CLIENTI | AM8: 22 | AN8: 5 | AO8: 2 | AP8: 9904 | AS8: COND.USO DOM LIBERO | AU8: SWITCH | AV8: C1 | AW8: 1 | AX8: 00001 | AY8: =MID(BN8,1,4) -> 0 | BB8: 12 | BC8: =IF(BD8<=4999,"04","12") -> 04 | BD8: ='ALLEGATO 1 CONDOMINI'!P23 -> 0 | BK8: RID | BL8: 30DF | BM8: ND | BN8: ='ALLEGATO 1 CONDOMINI'!L23 -> 0 | BO8: ='ALLEGATO 1 CONDOMINI'!O23 -> 0 | BQ8: =P8 -> #N/A | BR8: =Q8 -> 0 | BS8: =R8 -> #N/A | BT8: =S8 -> #N/A | BU8: =T8 -> 0 | BV8: =U8 -> 0 | BW8: =V8 -> 0 | CB8: ='ALLEGATO 1 CONDOMINI'!N23 -> 0 | CQ8: AMMINISTRATORE | DE8: ATTIVA | DG8: =AF8 -> 0 | DH8: =AG8 -> 0 | DI8: ='ALLEGATO 1 CONDOMINI'!K23 -> 0 | DJ8: B5746 | ED8: =VLOOKUP('ALLEGATO 1 CONDOMINI'!M23,Venditori!B:E,4,FALSE) -> #N/A | EI8: G | EK8: profilo di prelievo | EL8: COND | EO8: =MID(D8,1,20) -> COND. | ER8: Controparte Commerciale & UDD | EV8: Core | FT8: 97.00.02 | GJ8: NO | GK8: NO | GL8: NO | GN8: 28 | GO8: NO | GP8: ITA
D9: =_xlfn.CONCAT('ALLEGATO 1 CONDOMINI'!B24,'ALLEGATO 1 CONDOMINI'!C24) -> COND. | F9: ='ALLEGATO 1 CONDOMINI'!D24 -> 0 | K9: CLIENTI | L9: 22 | M9: CLI-RD | P9: =VLOOKUP(Q9,'Zone Istat'!A:E,2,FALSE) -> #N/A | Q9: ='ALLEGATO 1 CONDOMINI'!I24 -> 0 | R9: =VLOOKUP(Q9,'[1]Zone Istat'!A:E,5,FALSE) -> #N/A | S9: =VLOOKUP(Q9,'Zone Istat'!A:E,4,FALSE) -> #N/A | T9: ='ALLEGATO 1 CONDOMINI'!E24 -> 0 | U9: ='ALLEGATO 1 CONDOMINI'!F24 -> 0 | V9: ='ALLEGATO 1 CONDOMINI'!G24 -> 0 | AA9: RID | AB9: 30DF | AC9: COND | AD9: NO | AE9: ND | AJ9: =D9 -> COND. | AL9: CLIENTI | AM9: 22 | AN9: 5 | AO9: 2 | AP9: 9904 | AS9: COND.USO DOM LIBERO | AU9: SWITCH | AV9: C1 | AW9: 1 | AX9: 00001 | AY9: =MID(BN9,1,4) -> 0 | BB9: 12 | BC9: =IF(BD9<=4999,"04","12") -> 04 | BD9: ='ALLEGATO 1 CONDOMINI'!P24 -> 0 | BK9: RID | BL9: 30DF | BM9: ND | BN9: ='ALLEGATO 1 CONDOMINI'!L24 -> 0 | BO9: ='ALLEGATO 1 CONDOMINI'!O24 -> 0 | BP9: =P9 -> #N/A | BQ9: =Q9 -> 0 | BR9: =R9 -> #N/A | BS9: =S9 -> #N/A | BU9: =T9 -> 0 | BV9: =U9 -> 0 | BW9: =V9 -> 0 | CB9: ='ALLEGATO 1 CONDOMINI'!N24 -> 0 | CQ9: AMMINISTRATORE | DE9: ATTIVA | DG9: =AF9 -> 0 | DH9: =AG9 -> 0 | DI9: ='ALLEGATO 1 CONDOMINI'!K24 -> 0 | DJ9: B5746 | ED9: =VLOOKUP('ALLEGATO 1 CONDOMINI'!M24,Venditori!B:E,4,FALSE) -> #N/A | EI9: G | EK9: profilo di prelievo | EL9: COND | EO9: =MID(D9,1,20) -> COND. | ER9: Controparte Commerciale & UDD | EV9: Core | FT9: 97.00.02 | GJ9: NO | GK9: NO | GL9: NO | GN9: 28 | GO9: NO | GP9: ITA
D10: =_xlfn.CONCAT('ALLEGATO 1 CONDOMINI'!B25,'ALLEGATO 1 CONDOMINI'!C25) -> COND. | F10: ='ALLEGATO 1 CONDOMINI'!D25 -> 0 | K10: CLIENTI | L10: 22 | M10: CLI-RD | P10: =VLOOKUP(Q10,'Zone Istat'!A:E,2,FALSE) -> #N/A | Q10: ='ALLEGATO 1 CONDOMINI'!I25 -> 0 | R10: =VLOOKUP(Q10,'[1]Zone Istat'!A:E,5,FALSE) -> #N/A | S10: =VLOOKUP(Q10,'Zone Istat'!A:E,4,FALSE) -> #N/A | T10: ='ALLEGATO 1 CONDOMINI'!E25 -> 0 | U10: ='ALLEGATO 1 CONDOMINI'!F25 -> 0 | V10: ='ALLEGATO 1 CONDOMINI'!G25 -> 0 | AA10: RID | AB10: 30DF | AC10: COND | AD10: NO | AE10: ND | AJ10: =D10 -> COND. | AL10: CLIENTI | AM10: 22 | AN10: 5 | AO10: 2 | AP10: 9904 | AS10: COND.USO DOM LIBERO | AU10: SWITCH | AV10: C1 | AW10: 1 | AX10: 00001 | AY10: =MID(BN10,1,4) -> 0 | BB10: 12 | BC10: =IF(BD10<=4999,"04","12") -> 04 | BD10: ='ALLEGATO 1 CONDOMINI'!P25 -> 0 | BK10: RID | BL10: 30DF | BM10: ND | BN10: ='ALLEGATO 1 CONDOMINI'!L25 -> 0 | BO10: ='ALLEGATO 1 CONDOMINI'!O25 -> 0 | BP10: =P10 -> #N/A | BQ10: =Q10 -> 0 | BR10: =R10 -> #N/A | BS10: =S10 -> #N/A | BU10: =T10 -> 0 | BV10: =U10 -> 0 | BW10: =V10 -> 0 | CB10: ='ALLEGATO 1 CONDOMINI'!N25 -> 0 | CQ10: AMMINISTRATORE | DE10: ATTIVA | DG10: =AF10 -> 0 | DH10: =AG10 -> 0 | DI10: ='ALLEGATO 1 CONDOMINI'!K25 -> 0 | DJ10: B5746 | ED10: =VLOOKUP('ALLEGATO 1 CONDOMINI'!M25,Venditori!B:E,4,FALSE) -> #N/A | EI10: G | EK10: profilo di prelievo | EL10: COND | EO10: =MID(D10,1,20) -> COND. | ER10: Controparte Commerciale & UDD | EV10: Core | FT10: 97.00.02 | GJ10: NO | GK10: NO | GL10: NO | GN10: 28 | GO10: NO | GP10: ITA
D11: =_xlfn.CONCAT('ALLEGATO 1 CONDOMINI'!B26,'ALLEGATO 1 CONDOMINI'!C26) -> COND. | F11: ='ALLEGATO 1 CONDOMINI'!D26 -> 0 | K11: CLIENTI | L11: 22 | M11: CLI-RD | P11: =VLOOKUP(Q11,'Zone Istat'!A:E,2,FALSE) -> #N/A | Q11: ='ALLEGATO 1 CONDOMINI'!I26 -> 0 | R11: =VLOOKUP(Q11,'[1]Zone Istat'!A:E,5,FALSE) -> #N/A | S11: =VLOOKUP(Q11,'Zone Istat'!A:E,4,FALSE) -> #N/A | T11: ='ALLEGATO 1 CONDOMINI'!E26 -> 0 | U11: ='ALLEGATO 1 CONDOMINI'!F26 -> 0 | V11: ='ALLEGATO 1 CONDOMINI'!G26 -> 0 | AA11: RID | AB11: 30DF | AC11: COND | AD11: NO | AE11: ND | AJ11: =D11 -> COND. | AL11: CLIENTI | AM11: 22 | AN11: 5 | AO11: 2 | AP11: 9904 | AS11: COND.USO DOM LIBERO | AU11: SWITCH | AV11: C1 | AW11: 1 | AX11: 00001 | AY11: =MID(BN11,1,4) -> 0 | BB11: 12 | BC11: =IF(BD11<=4999,"04","12") -> 04 | BD11: ='ALLEGATO 1 CONDOMINI'!P26 -> 0 | BK11: RID | BL11: 30DF | BM11: ND | BN11: ='ALLEGATO 1 CONDOMINI'!L26 -> 0 | BO11: ='ALLEGATO 1 CONDOMINI'!O26 -> 0 | BU11: =T11 -> 0 | BV11: =U11 -> 0 | BW11: =V11 -> 0 | CB11: ='ALLEGATO 1 CONDOMINI'!N26 -> 0 | CQ11: AMMINISTRATORE | DE11: ATTIVA | DG11: =AF11 -> 0 | DH11: =AG11 -> 0 | DI11: ='ALLEGATO 1 CONDOMINI'!K26 -> 0 | DJ11: B5746 | ED11: =VLOOKUP('ALLEGATO 1 CONDOMINI'!M26,Venditori!B:E,4,FALSE) -> #N/A | EI11: G | EK11: profilo di prelievo | EL11: COND | EO11: =MID(D11,1,20) -> COND. | ER11: Controparte Commerciale & UDD | EV11: Core | FT11: 97.00.02 | GJ11: NO | GK11: NO | GL11: NO | GN11: 28 | GO11: NO | GP11: ITA
D12: =_xlfn.CONCAT('ALLEGATO 1 CONDOMINI'!B27,'ALLEGATO 1 CONDOMINI'!C27) -> COND. | F12: ='ALLEGATO 1 CONDOMINI'!D27 -> 0 | K12: CLIENTI | L12: 22 | M12: CLI-RD | P12: =VLOOKUP(Q12,'Zone Istat'!A:E,2,FALSE) -> #N/A | Q12: ='ALLEGATO 1 CONDOMINI'!I27 -> 0 | R12: =VLOOKUP(Q12,'[1]Zone Istat'!A:E,5,FALSE) -> #N/A | S12: =VLOOKUP(Q12,'Zone Istat'!A:E,4,FALSE) -> #N/A | T12: ='ALLEGATO 1 CONDOMINI'!E27 -> 0 | U12: ='ALLEGATO 1 CONDOMINI'!F27 -> 0 | V12: ='ALLEGATO 1 CONDOMINI'!G27 -> 0 | AA12: RID | AB12: 30DF | AC12: COND | AD12: NO | AE12: ND | AJ12: =D12 -> COND. | AL12: CLIENTI | AM12: 22 | AN12: 5 | AO12: 2 | AP12: 9904 | AS12: COND.USO DOM LIBERO | AU12: SWITCH | AV12: C1 | AW12: 1 | AX12: 00001 | AY12: =MID(BN12,1,4) -> 0 | BB12: 12 | BC12: =IF(BD12<=4999,"04","12") -> 04 | BD12: ='ALLEGATO 1 CONDOMINI'!P27 -> 0 | BK12: RID | BL12: 30DF | BM12: ND | BN12: ='ALLEGATO 1 CONDOMINI'!L27 -> 0 | BO12: ='ALLEGATO 1 CONDOMINI'!O27 -> 0 | BU12: =T12 -> 0 | BV12: =U12 -> 0 | BW12: =V12 -> 0 | CB12: ='ALLEGATO 1 CONDOMINI'!N27 -> 0 | CQ12: AMMINISTRATORE | DE12: ATTIVA | DG12: =AF12 -> 0 | DH12: =AG12 -> 0 | DI12: ='ALLEGATO 1 CONDOMINI'!K27 -> 0 | DJ12: B5746 | ED12: =VLOOKUP('ALLEGATO 1 CONDOMINI'!M27,Venditori!B:E,4,FALSE) -> #N/A | EI12: G | EK12: profilo di prelievo | EL12: COND | EO12: =MID(D12,1,20) -> COND. | ER12: Controparte Commerciale & UDD | EV12: Core | FT12: 97.00.02 | GJ12: NO | GK12: NO | GL12: NO | GN12: 28 | GO12: NO | GP12: ITA
D13: =_xlfn.CONCAT('[1]ALLEGATO 1 CONDOMINI'!B28,'[1]ALLEGATO 1 CONDOMINI'!C28) -> COND. | F13: ='ALLEGATO 1 CONDOMINI'!D28 -> 0 | K13: CLIENTI | L13: 22 | M13: CLI-RD | P13: =VLOOKUP(Q13,'[1]Zone Istat'!A:E,2,FALSE) -> #N/A | Q13: ='[1]ALLEGATO 1 CONDOMINI'!G28 -> 0 | R13: =VLOOKUP(Q13,'[1]Zone Istat'!A:E,5,FALSE) -> #N/A | S13: =VLOOKUP(Q13,'Zone Istat'!A:E,4,FALSE) -> #N/A | T13: ='ALLEGATO 1 CONDOMINI'!E28 -> 0 | U13: ='ALLEGATO 1 CONDOMINI'!F28 -> 0 | V13: ='ALLEGATO 1 CONDOMINI'!G28 -> 0 | AA13: RID | AB13: 30DF | AC13: COND | AD13: NO | AE13: ND | AJ13: =D13 -> COND. | AL13: CLIENTI | AM13: 22 | AN13: 5 | AO13: 2 | AP13: 9904 | AS13: COND.USO DOM LIBERO | AU13: SWITCH | AV13: C1 | AW13: 1 | AX13: 00001 | AY13: =MID(BN13,1,4) -> 0 | BB13: 12 | BC13: =IF(BD13<=4999,"04","12") -> 04 | BD13: ='ALLEGATO 1 CONDOMINI'!P28 -> 0 | BK13: RID | BL13: 30DF | BM13: ND | BN13: ='ALLEGATO 1 CONDOMINI'!L28 -> 0 | BO13: ='ALLEGATO 1 CONDOMINI'!O28 -> 0 | BU13: =T13 -> 0 | BV13: =U13 -> 0 | BW13: =V13 -> 0 | CB13: ='ALLEGATO 1 CONDOMINI'!N28 -> 0 | CQ13: AMMINISTRATORE | DE13: ATTIVA | DG13: =AF13 -> 0 | DH13: =AG13 -> 0 | DI13: ='ALLEGATO 1 CONDOMINI'!K28 -> 0 | DJ13: B5746 | ED13: =VLOOKUP('[1]ALLEGATO 1 CONDOMINI'!K28,[1]Venditori!B:E,4,FALSE) -> #N/A | EI13: G | EK13: profilo di prelievo | EL13: COND | EO13: =MID(D13,1,20) -> COND. | ER13: Controparte Commerciale & UDD | EV13: Core | FT13: 97.00.02 | GJ13: NO | GK13: NO | GL13: NO | GN13: 28 | GO13: NO | GP13: ITA
D14: =_xlfn.CONCAT('[1]ALLEGATO 1 CONDOMINI'!B29,'[1]ALLEGATO 1 CONDOMINI'!C29) -> #REF! | F14: ='ALLEGATO 1 CONDOMINI'!D29 -> 0 | K14: CLIENTI | L14: 22 | M14: CLI-RD | P14: =VLOOKUP(Q14,'[1]Zone Istat'!A:E,2,FALSE) -> #REF! | Q14: ='[1]ALLEGATO 1 CONDOMINI'!G29 -> #REF! | R14: =VLOOKUP(Q14,'[1]Zone Istat'!A:E,5,FALSE) -> #REF! | S14: =VLOOKUP(Q14,'Zone Istat'!A:E,4,FALSE) -> #REF! | T14: ='ALLEGATO 1 CONDOMINI'!E29 -> 0 | U14: ='ALLEGATO 1 CONDOMINI'!F29 -> 0 | V14: ='ALLEGATO 1 CONDOMINI'!G29 -> 0 | AA14: RID | AB14: 30DF | AC14: COND | AD14: NO | AE14: ND | AJ14: =D14 -> #REF! | AL14: CLIENTI | AM14: 22 | AN14: 5 | AO14: 2 | AP14: 9904 | AS14: COND.USO DOM LIBERO | AU14: SWITCH | AV14: C1 | AW14: 1 | AX14: 00001 | AY14: =MID(BN14,1,4) -> 0 | BB14: 12 | BC14: =IF(BD14<=4999,"04","12") -> 04 | BD14: ='ALLEGATO 1 CONDOMINI'!P29 -> 0 | BK14: RID | BL14: 30DF | BM14: ND | BN14: ='ALLEGATO 1 CONDOMINI'!L29 -> 0 | BO14: ='ALLEGATO 1 CONDOMINI'!O29 -> 0 | BU14: =T14 -> 0 | BV14: =U14 -> 0 | BW14: =V14 -> 0 | CB14: ='ALLEGATO 1 CONDOMINI'!N29 -> 0 | CQ14: AMMINISTRATORE | DE14: ATTIVA | DG14: =AF14 -> 0 | DH14: =AG14 -> 0 | DI14: ='ALLEGATO 1 CONDOMINI'!K29 -> 0 | DJ14: B5746 | ED14: =VLOOKUP('[1]ALLEGATO 1 CONDOMINI'!K29,[1]Venditori!B:E,4,FALSE) -> #REF! | EI14: G | EK14: profilo di prelievo | EL14: COND | EO14: =MID(D14,1,20) -> #REF! | ER14: Controparte Commerciale & UDD | EV14: Core | FT14: 97.00.02 | GJ14: NO | GK14: NO | GL14: NO | GN14: 28 | GO14: NO | GP14: ITA
D15: =_xlfn.CONCAT('[1]ALLEGATO 1 CONDOMINI'!B30,'[1]ALLEGATO 1 CONDOMINI'!C30) -> #REF! | F15: ='ALLEGATO 1 CONDOMINI'!D30 -> 0 | K15: CLIENTI | L15: 22 | M15: CLI-RD | P15: =VLOOKUP(Q15,'[1]Zone Istat'!A:E,2,FALSE) -> #REF! | Q15: ='[1]ALLEGATO 1 CONDOMINI'!G30 -> #REF! | R15: =VLOOKUP(Q15,'[1]Zone Istat'!A:E,5,FALSE) -> #REF! | S15: =VLOOKUP(Q15,'Zone Istat'!A:E,4,FALSE) -> #REF! | T15: ='ALLEGATO 1 CONDOMINI'!E30 -> 0 | U15: ='ALLEGATO 1 CONDOMINI'!F30 -> 0 | V15: ='ALLEGATO 1 CONDOMINI'!G30 -> 0 | AA15: RID | AB15: 30DF | AC15: COND | AD15: NO | AE15: ND | AJ15: =D15 -> #REF! | AL15: CLIENTI | AM15: 22 | AN15: 5 | AO15: 2 | AP15: 9904 | AS15: COND.USO DOM LIBERO | AU15: SWITCH | AV15: C1 | AW15: 1 | AX15: 00001 | AY15: =MID(BN15,1,4) -> 0 | BB15: 12 | BC15: =IF(BD15<=4999,"04","12") -> 04 | BD15: ='ALLEGATO 1 CONDOMINI'!P30 -> 0 | BK15: RID | BL15: 30DF | BM15: ND | BN15: ='ALLEGATO 1 CONDOMINI'!L30 -> 0 | BO15: ='ALLEGATO 1 CONDOMINI'!O30 -> 0 | BU15: =T15 -> 0 | BV15: =U15 -> 0 | BW15: =V15 -> 0 | CB15: ='ALLEGATO 1 CONDOMINI'!N30 -> 0 | CQ15: AMMINISTRATORE | DE15: ATTIVA | DG15: =AF15 -> 0 | DH15: =AG15 -> 0 | DI15: ='ALLEGATO 1 CONDOMINI'!K30 -> 0 | DJ15: B5746 | ED15: =VLOOKUP('[1]ALLEGATO 1 CONDOMINI'!K30,[1]Venditori!B:E,4,FALSE) -> #REF! | EI15: G | EK15: profilo di prelievo | EL15: COND | EO15: =MID(D15,1,20) -> #REF! | ER15: Controparte Commerciale & UDD | EV15: Core | FT15: 97.00.02 | GJ15: NO | GK15: NO | GL15: NO | GN15: 28 | GO15: NO | GP15: ITA
D16: =_xlfn.CONCAT('[1]ALLEGATO 1 CONDOMINI'!B31,'[1]ALLEGATO 1 CONDOMINI'!C31) -> #REF! | F16: ='ALLEGATO 1 CONDOMINI'!D31 -> 0 | K16: CLIENTI | L16: 22 | M16: CLI-RD | P16: =VLOOKUP(Q16,'[1]Zone Istat'!A:E,2,FALSE) -> #REF! | Q16: ='[1]ALLEGATO 1 CONDOMINI'!G31 -> #REF! | R16: =VLOOKUP(Q16,'[1]Zone Istat'!A:E,5,FALSE) -> #REF! | S16: =VLOOKUP(Q16,'Zone Istat'!A:E,4,FALSE) -> #REF! | T16: ='ALLEGATO 1 CONDOMINI'!E31 -> 0 | U16: ='ALLEGATO 1 CONDOMINI'!F31 -> 0 | V16: ='ALLEGATO 1 CONDOMINI'!G31 -> 0 | AA16: RID | AB16: 30DF | AC16: COND | AD16: NO | AE16: ND | AJ16: =D16 -> #REF! | AL16: CLIENTI | AM16: 22 | AN16: 5 | AO16: 2 | AP16: 9904 | AS16: COND.USO DOM LIBERO | AU16: SWITCH | AV16: C1 | AW16: 1 | AX16: 00001 | AY16: =MID(BN16,1,4) -> 0 | BB16: 12 | BC16: =IF(BD16<=4999,"04","12") -> 04 | BD16: ='ALLEGATO 1 CONDOMINI'!P31 -> 0 | BK16: RID | BL16: 30DF | BM16: ND | BN16: ='ALLEGATO 1 CONDOMINI'!L31 -> 0 | BO16: ='ALLEGATO 1 CONDOMINI'!O31 -> 0 | BU16: =T16 -> 0 | BV16: =U16 -> 0 | BW16: =V16 -> 0 | CB16: ='ALLEGATO 1 CONDOMINI'!N31 -> 0 | CQ16: AMMINISTRATORE | DE16: ATTIVA | DG16: =AF16 -> 0 | DH16: =AG16 -> 0 | DI16: ='ALLEGATO 1 CONDOMINI'!K31 -> 0 | DJ16: B5746 | ED16: =VLOOKUP('[1]ALLEGATO 1 CONDOMINI'!K31,[1]Venditori!B:E,4,FALSE) -> #REF! | EI16: G | EK16: profilo di prelievo | EL16: COND | EO16: =MID(D16,1,20) -> #REF! | ER16: Controparte Commerciale & UDD | EV16: Core | FT16: 97.00.02 | GJ16: NO | GK16: NO | GL16: NO | GN16: 28 | GO16: NO | GP16: ITA
D17: =_xlfn.CONCAT('[1]ALLEGATO 1 CONDOMINI'!B32,'[1]ALLEGATO 1 CONDOMINI'!C32) -> #REF! | F17: ='ALLEGATO 1 CONDOMINI'!D32 -> 0 | K17: CLIENTI | L17: 22 | M17: CLI-RD | P17: =VLOOKUP(Q17,'[1]Zone Istat'!A:E,2,FALSE) -> #REF! | Q17: ='[1]ALLEGATO 1 CONDOMINI'!G32 -> #REF! | R17: =VLOOKUP(Q17,'[1]Zone Istat'!A:E,5,FALSE) -> #REF! | S17: =VLOOKUP(Q17,'Zone Istat'!A:E,4,FALSE) -> #REF! | T17: ='ALLEGATO 1 CONDOMINI'!E32 -> 0 | U17: ='ALLEGATO 1 CONDOMINI'!F32 -> 0 | V17: ='ALLEGATO 1 CONDOMINI'!G32 -> 0 | AA17: RID | AB17: 30DF | AC17: COND | AD17: NO | AE17: ND | AJ17: =D17 -> #REF! | AL17: CLIENTI | AM17: 22 | AN17: 5 | AO17: 2 | AP17: 9904 | AS17: COND.USO DOM LIBERO | AU17: SWITCH | AV17: C1 | AW17: 1 | AX17: 00001 | AY17: =MID(BN17,1,4) -> 0 | BB17: 12 | BC17: =IF(BD17<=4999,"04","12") -> 04 | BD17: ='ALLEGATO 1 CONDOMINI'!P32 -> 0 | BK17: RID | BL17: 30DF | BM17: ND | BN17: ='ALLEGATO 1 CONDOMINI'!L32 -> 0 | BO17: ='ALLEGATO 1 CONDOMINI'!O32 -> 0 | BU17: =T17 -> 0 | BV17: =U17 -> 0 | BW17: =V17 -> 0 | CB17: ='ALLEGATO 1 CONDOMINI'!N32 -> 0 | CQ17: AMMINISTRATORE | DE17: ATTIVA | DG17: =AF17 -> 0 | DH17: =AG17 -> 0 | DI17: ='ALLEGATO 1 CONDOMINI'!K32 -> 0 | DJ17: B5746 | ED17: =VLOOKUP('[1]ALLEGATO 1 CONDOMINI'!K32,[1]Venditori!B:E,4,FALSE) -> #REF! | EI17: G | EK17: profilo di prelievo | EL17: COND | EO17: =MID(D17,1,20) -> #REF! | ER17: Controparte Commerciale & UDD | EV17: Core | FT17: 97.00.02 | GJ17: NO | GK17: NO | GL17: NO | GN17: 28 | GO17: NO | GP17: ITA
D18: =_xlfn.CONCAT('[1]ALLEGATO 1 CONDOMINI'!B33,'[1]ALLEGATO 1 CONDOMINI'!C33) -> #REF! | F18: ='ALLEGATO 1 CONDOMINI'!D33 -> 0 | K18: CLIENTI | L18: 22 | M18: CLI-RD | P18: =VLOOKUP(Q18,'[1]Zone Istat'!A:E,2,FALSE) -> #REF! | Q18: ='[1]ALLEGATO 1 CONDOMINI'!G33 -> #REF! | R18: =VLOOKUP(Q18,'[1]Zone Istat'!A:E,5,FALSE) -> #REF! | S18: =VLOOKUP(Q18,'Zone Istat'!A:E,4,FALSE) -> #REF! | T18: ='ALLEGATO 1 CONDOMINI'!E33 -> 0 | U18: ='ALLEGATO 1 CONDOMINI'!F33 -> 0 | V18: ='ALLEGATO 1 CONDOMINI'!G33 -> 0 | AA18: RID | AB18: 30DF | AC18: COND | AD18: NO | AE18: ND | AJ18: =D18 -> #REF! | AL18: CLIENTI | AM18: 22 | AN18: 5 | AO18: 2 | AP18: 9904 | AS18: COND.USO DOM LIBERO | AU18: SWITCH | AV18: C1 | AW18: 1 | AX18: 00001 | AY18: =MID(BN18,1,4) -> 0 | BB18: 12 | BC18: =IF(BD18<=4999,"04","12") -> 04 | BD18: ='ALLEGATO 1 CONDOMINI'!P33 -> 0 | BK18: RID | BL18: 30DF | BM18: ND | BN18: ='ALLEGATO 1 CONDOMINI'!L33 -> 0 | BO18: ='ALLEGATO 1 CONDOMINI'!O33 -> 0 | BU18: =T18 -> 0 | BV18: =U18 -> 0 | BW18: =V18 -> 0 | CB18: ='ALLEGATO 1 CONDOMINI'!N33 -> 0 | CQ18: AMMINISTRATORE | DE18: ATTIVA | DG18: =AF18 -> 0 | DH18: =AG18 -> 0 | DI18: ='ALLEGATO 1 CONDOMINI'!K33 -> 0 | DJ18: B5746 | ED18: =VLOOKUP('[1]ALLEGATO 1 CONDOMINI'!K33,[1]Venditori!B:E,4,FALSE) -> #REF! | EI18: G | EK18: profilo di prelievo | EL18: COND | EO18: =MID(D18,1,20) -> #REF! | ER18: Controparte Commerciale & UDD | EV18: Core | FT18: 97.00.02 | GJ18: NO | GK18: NO | GL18: NO | GN18: 28 | GO18: NO | GP18: ITA
D19: =_xlfn.CONCAT('[1]ALLEGATO 1 CONDOMINI'!B34,'[1]ALLEGATO 1 CONDOMINI'!C34) -> #REF! | F19: ='ALLEGATO 1 CONDOMINI'!D34 -> 0 | K19: CLIENTI | L19: 22 | M19: CLI-RD | P19: =VLOOKUP(Q19,'[1]Zone Istat'!A:E,2,FALSE) -> #REF! | Q19: ='[1]ALLEGATO 1 CONDOMINI'!G34 -> #REF! | R19: =VLOOKUP(Q19,'[1]Zone Istat'!A:E,5,FALSE) -> #REF! | S19: =VLOOKUP(Q19,'Zone Istat'!A:E,4,FALSE) -> #REF! | T19: ='ALLEGATO 1 CONDOMINI'!E34 -> 0 | U19: ='ALLEGATO 1 CONDOMINI'!F34 -> 0 | V19: ='ALLEGATO 1 CONDOMINI'!G34 -> 0 | AA19: RID | AB19: 30DF | AC19: COND | AD19: NO | AE19: ND | AJ19: =D19 -> #REF! | AL19: CLIENTI | AM19: 22 | AN19: 5 | AO19: 2 | AP19: 9904 | AS19: COND.USO DOM LIBERO | AU19: SWITCH | AV19: C1 | AW19: 1 | AX19: 00001 | AY19: =MID(BN19,1,4) -> 0 | BB19: 12 | BC19: =IF(BD19<=4999,"04","12") -> 04 | BD19: ='ALLEGATO 1 CONDOMINI'!P34 -> 0 | BK19: RID | BL19: 30DF | BM19: ND | BN19: ='ALLEGATO 1 CONDOMINI'!L34 -> 0 | BO19: ='ALLEGATO 1 CONDOMINI'!O34 -> 0 | BU19: =T19 -> 0 | BV19: =U19 -> 0 | BW19: =V19 -> 0 | CB19: ='ALLEGATO 1 CONDOMINI'!N34 -> 0 | CQ19: AMMINISTRATORE | DE19: ATTIVA | DG19: =AF19 -> 0 | DH19: =AG19 -> 0 | DI19: ='ALLEGATO 1 CONDOMINI'!K34 -> 0 | DJ19: B5746 | ED19: =VLOOKUP('[1]ALLEGATO 1 CONDOMINI'!K34,[1]Venditori!B:E,4,FALSE) -> #REF! | EI19: G | EK19: profilo di prelievo | EL19: COND | EO19: =MID(D19,1,20) -> #REF! | ER19: Controparte Commerciale & UDD | EV19: Core | FT19: 97.00.02 | GJ19: NO | GK19: NO | GL19: NO | GN19: 28 | GO19: NO | GP19: ITA
D20: =_xlfn.CONCAT('[1]ALLEGATO 1 CONDOMINI'!B35,'[1]ALLEGATO 1 CONDOMINI'!C35) -> #REF! | F20: ='ALLEGATO 1 CONDOMINI'!D35 -> 0 | K20: CLIENTI | L20: 22 | M20: CLI-RD | P20: =VLOOKUP(Q20,'[1]Zone Istat'!A:E,2,FALSE) -> #REF! | Q20: ='[1]ALLEGATO 1 CONDOMINI'!G35 -> #REF! | R20: =VLOOKUP(Q20,'[1]Zone Istat'!A:E,5,FALSE) -> #REF! | S20: =VLOOKUP(Q20,'Zone Istat'!A:E,4,FALSE) -> #REF! | T20: ='ALLEGATO 1 CONDOMINI'!E35 -> 0 | U20: ='ALLEGATO 1 CONDOMINI'!F35 -> 0 | V20: ='ALLEGATO 1 CONDOMINI'!G35 -> 0 | AA20: RID | AB20: 30DF | AC20: COND | AD20: NO | AE20: ND | AJ20: =D20 -> #REF! | AL20: CLIENTI | AM20: 22 | AN20: 5 | AO20: 2 | AP20: 9904 | AS20: COND.USO DOM LIBERO | AU20: SWITCH | AV20: C1 | AW20: 1 | AX20: 00001 | AY20: =MID(BN20,1,4) -> 0 | BB20: 12 | BC20: =IF(BD20<=4999,"04","12") -> 04 | BD20: ='ALLEGATO 1 CONDOMINI'!P35 -> 0 | BK20: RID | BL20: 30DF | BM20: ND | BN20: ='ALLEGATO 1 CONDOMINI'!L35 -> 0 | BO20: ='ALLEGATO 1 CONDOMINI'!O35 -> 0 | BU20: =T20 -> 0 | BV20: =U20 -> 0 | BW20: =V20 -> 0 | CB20: ='ALLEGATO 1 CONDOMINI'!N35 -> 0 | CQ20: AMMINISTRATORE | DE20: ATTIVA | DG20: =AF20 -> 0 | DH20: =AG20 -> 0 | DI20: ='ALLEGATO 1 CONDOMINI'!K35 -> 0 | DJ20: B5746 | ED20: =VLOOKUP('[1]ALLEGATO 1 CONDOMINI'!K35,[1]Venditori!B:E,4,FALSE) -> #REF! | EI20: G | EK20: profilo di prelievo | EL20: COND | EO20: =MID(D20,1,20) -> #REF! | ER20: Controparte Commerciale & UDD | EV20: Core | FT20: 97.00.02 | GJ20: NO | GK20: NO | GL20: NO | GN20: 28 | GO20: NO | GP20: ITA
D21: =_xlfn.CONCAT('[1]ALLEGATO 1 CONDOMINI'!B36,'[1]ALLEGATO 1 CONDOMINI'!C36) -> #REF! | F21: ='ALLEGATO 1 CONDOMINI'!D36 -> 0 | K21: CLIENTI | L21: 22 | M21: CLI-RD | P21: =VLOOKUP(Q21,'[1]Zone Istat'!A:E,2,FALSE) -> #REF! | Q21: ='[1]ALLEGATO 1 CONDOMINI'!G36 -> #REF! | R21: =VLOOKUP(Q21,'[1]Zone Istat'!A:E,5,FALSE) -> #REF! | S21: =VLOOKUP(Q21,'Zone Istat'!A:E,4,FALSE) -> #REF! | T21: ='ALLEGATO 1 CONDOMINI'!E36 -> 0 | U21: ='ALLEGATO 1 CONDOMINI'!F36 -> 0 | V21: ='ALLEGATO 1 CONDOMINI'!G36 -> 0 | AA21: RID | AB21: 30DF | AC21: COND | AD21: NO | AE21: ND | AJ21: =D21 -> #REF! | AL21: CLIENTI | AM21: 22 | AN21: 5 | AO21: 2 | AP21: 9904 | AS21: COND.USO DOM LIBERO | AU21: SWITCH | AV21: C1 | AW21: 1 | AX21: 00001 | AY21: =MID(BN21,1,4) -> 0 | BB21: 12 | BC21: =IF(BD21<=4999,"04","12") -> 04 | BD21: ='ALLEGATO 1 CONDOMINI'!P36 -> 0 | BK21: RID | BL21: 30DF | BM21: ND | BN21: ='ALLEGATO 1 CONDOMINI'!L36 -> 0 | BO21: ='ALLEGATO 1 CONDOMINI'!O36 -> 0 | BU21: =T21 -> 0 | BV21: =U21 -> 0 | BW21: =V21 -> 0 | CB21: ='ALLEGATO 1 CONDOMINI'!N36 -> 0 | CQ21: AMMINISTRATORE | DE21: ATTIVA | DG21: =AF21 -> 0 | DH21: =AG21 -> 0 | DI21: ='ALLEGATO 1 CONDOMINI'!K36 -> 0 | DJ21: B5746 | ED21: =VLOOKUP('[1]ALLEGATO 1 CONDOMINI'!K36,[1]Venditori!B:E,4,FALSE) -> #REF! | EI21: G | EK21: profilo di prelievo | EL21: COND | EO21: =MID(D21,1,20) -> #REF! | ER21: Controparte Commerciale & UDD | EV21: Core | FT21: 97.00.02 | GJ21: NO | GK21: NO | GL21: NO | GN21: 28 | GO21: NO | GP21: ITA
D22: =_xlfn.CONCAT('[1]ALLEGATO 1 CONDOMINI'!B37,'[1]ALLEGATO 1 CONDOMINI'!C37) -> #REF! | F22: ='ALLEGATO 1 CONDOMINI'!D37 -> 0 | K22: CLIENTI | L22: 22 | M22: CLI-RD | P22: =VLOOKUP(Q22,'[1]Zone Istat'!A:E,2,FALSE) -> #REF! | Q22: ='[1]ALLEGATO 1 CONDOMINI'!G37 -> #REF! | R22: =VLOOKUP(Q22,'[1]Zone Istat'!A:E,5,FALSE) -> #REF! | S22: =VLOOKUP(Q22,'Zone Istat'!A:E,4,FALSE) -> #REF! | T22: ='ALLEGATO 1 CONDOMINI'!E37 -> 0 | U22: ='ALLEGATO 1 CONDOMINI'!F37 -> 0 | V22: ='ALLEGATO 1 CONDOMINI'!G37 -> 0 | AA22: RID | AB22: 30DF | AC22: COND | AD22: NO | AE22: ND | AJ22: =D22 -> #REF! | AL22: CLIENTI | AM22: 22 | AN22: 5 | AO22: 2 | AP22: 9904 | AS22: COND.USO DOM LIBERO | AU22: SWITCH | AV22: C1 | AW22: 1 | AX22: 00001 | AY22: =MID(BN22,1,4) -> 0 | BB22: 12 | BC22: =IF(BD22<=4999,"04","12") -> 04 | BD22: ='ALLEGATO 1 CONDOMINI'!P37 -> 0 | BK22: RID | BL22: 30DF | BM22: ND | BN22: ='ALLEGATO 1 CONDOMINI'!L37 -> 0 | BO22: ='ALLEGATO 1 CONDOMINI'!O37 -> 0 | BU22: =T22 -> 0 | BV22: =U22 -> 0 | BW22: =V22 -> 0 | CB22: ='ALLEGATO 1 CONDOMINI'!N37 -> 0 | CQ22: AMMINISTRATORE | DE22: ATTIVA | DG22: =AF22 -> 0 | DH22: =AG22 -> 0 | DI22: ='ALLEGATO 1 CONDOMINI'!K37 -> 0 | DJ22: B5746 | ED22: =VLOOKUP('[1]ALLEGATO 1 CONDOMINI'!K37,[1]Venditori!B:E,4,FALSE) -> #REF! | EI22: G | EK22: profilo di prelievo | EL22: COND | EO22: =MID(D22,1,20) -> #REF! | ER22: Controparte Commerciale & UDD | EV22: Core | FT22: 97.00.02 | GJ22: NO | GK22: NO | GL22: NO | GN22: 28 | GO22: NO | GP22: ITA
D23: =_xlfn.CONCAT('[1]ALLEGATO 1 CONDOMINI'!B38,'[1]ALLEGATO 1 CONDOMINI'!C38) -> #REF! | F23: ='ALLEGATO 1 CONDOMINI'!D38 -> 0 | K23: CLIENTI | L23: 22 | M23: CLI-RD | P23: =VLOOKUP(Q23,'[1]Zone Istat'!A:E,2,FALSE) -> #REF! | Q23: ='[1]ALLEGATO 1 CONDOMINI'!G38 -> #REF! | R23: =VLOOKUP(Q23,'[1]Zone Istat'!A:E,5,FALSE) -> #REF! | S23: =VLOOKUP(Q23,'Zone Istat'!A:E,4,FALSE) -> #REF! | T23: ='ALLEGATO 1 CONDOMINI'!E38 -> 0 | U23: ='ALLEGATO 1 CONDOMINI'!F38 -> 0 | V23: ='ALLEGATO 1 CONDOMINI'!G38 -> 0 | AA23: RID | AB23: 30DF | AC23: COND | AD23: NO | AE23: ND | AJ23: =D23 -> #REF! | AL23: CLIENTI | AM23: 22 | AN23: 5 | AO23: 2 | AP23: 9904 | AS23: COND.USO DOM LIBERO | AU23: SWITCH | AV23: C1 | AW23: 1 | AX23: 00001 | AY23: =MID(BN23,1,4) -> 0 | BB23: 12 | BC23: =IF(BD23<=4999,"04","12") -> 04 | BD23: ='ALLEGATO 1 CONDOMINI'!P38 -> 0 | BK23: RID | BL23: 30DF | BM23: ND | BN23: ='ALLEGATO 1 CONDOMINI'!L38 -> 0 | BO23: ='ALLEGATO 1 CONDOMINI'!O38 -> 0 | BU23: =T23 -> 0 | BV23: =U23 -> 0 | BW23: =V23 -> 0 | CB23: ='ALLEGATO 1 CONDOMINI'!N38 -> 0 | CQ23: AMMINISTRATORE | DE23: ATTIVA | DG23: =AF23 -> 0 | DH23: =AG23 -> 0 | DI23: ='ALLEGATO 1 CONDOMINI'!K38 -> 0 | DJ23: B5746 | ED23: =VLOOKUP('[1]ALLEGATO 1 CONDOMINI'!K38,[1]Venditori!B:E,4,FALSE) -> #REF! | EI23: G | EK23: profilo di prelievo | EL23: COND | EO23: =MID(D23,1,20) -> #REF! | ER23: Controparte Commerciale & UDD | EV23: Core | FT23: 97.00.02 | GJ23: NO | GK23: NO | GL23: NO | GN23: 28 | GO23: NO | GP23: ITA
D24: =_xlfn.CONCAT('[1]ALLEGATO 1 CONDOMINI'!B39,'[1]ALLEGATO 1 CONDOMINI'!C39) -> #REF! | F24: ='ALLEGATO 1 CONDOMINI'!D39 -> 0 | K24: CLIENTI | L24: 22 | M24: CLI-RD | P24: =VLOOKUP(Q24,'[1]Zone Istat'!A:E,2,FALSE) -> #REF! | Q24: ='[1]ALLEGATO 1 CONDOMINI'!G39 -> #REF! | R24: =VLOOKUP(Q24,'[1]Zone Istat'!A:E,5,FALSE) -> #REF! | S24: =VLOOKUP(Q24,'Zone Istat'!A:E,4,FALSE) -> #REF! | T24: ='ALLEGATO 1 CONDOMINI'!E39 -> 0 | U24: ='ALLEGATO 1 CONDOMINI'!F39 -> 0 | V24: ='ALLEGATO 1 CONDOMINI'!G39 -> 0 | AA24: RID | AB24: 30DF | AC24: COND | AD24: NO | AE24: ND | AJ24: =D24 -> #REF! | AL24: CLIENTI | AM24: 22 | AN24: 5 | AO24: 2 | AP24: 9904 | AS24: COND.USO DOM LIBERO | AU24: SWITCH | AV24: C1 | AW24: 1 | AX24: 00001 | AY24: =MID(BN24,1,4) -> 0 | BB24: 12 | BC24: =IF(BD24<=4999,"04","12") -> 04 | BD24: ='ALLEGATO 1 CONDOMINI'!P39 -> 0 | BK24: RID | BL24: 30DF | BM24: ND | BN24: ='ALLEGATO 1 CONDOMINI'!L39 -> 0 | BO24: ='ALLEGATO 1 CONDOMINI'!O39 -> 0 | BU24: =T24 -> 0 | BV24: =U24 -> 0 | BW24: =V24 -> 0 | CB24: ='ALLEGATO 1 CONDOMINI'!N39 -> 0 | CQ24: AMMINISTRATORE | DE24: ATTIVA | DG24: =AF24 -> 0 | DH24: =AG24 -> 0 | DI24: ='ALLEGATO 1 CONDOMINI'!K39 -> 0 | DJ24: B5746 | ED24: =VLOOKUP('[1]ALLEGATO 1 CONDOMINI'!K39,[1]Venditori!B:E,4,FALSE) -> #REF! | EI24: G | EK24: profilo di prelievo | EL24: COND | EO24: =MID(D24,1,20) -> #REF! | ER24: Controparte Commerciale & UDD | EV24: Core | FT24: 97.00.02 | GJ24: NO | GK24: NO | GL24: NO | GN24: 28 | GO24: NO | GP24: ITA
D25: =_xlfn.CONCAT('[1]ALLEGATO 1 CONDOMINI'!B40,'[1]ALLEGATO 1 CONDOMINI'!C40) -> #REF! | F25: ='ALLEGATO 1 CONDOMINI'!D40 -> 0 | K25: CLIENTI | L25: 22 | M25: CLI-RD | P25: =VLOOKUP(Q25,'[1]Zone Istat'!A:E,2,FALSE) -> #REF! | Q25: ='[1]ALLEGATO 1 CONDOMINI'!G40 -> #REF! | R25: =VLOOKUP(Q25,'[1]Zone Istat'!A:E,5,FALSE) -> #REF! | S25: =VLOOKUP(Q25,'Zone Istat'!A:E,4,FALSE) -> #REF! | T25: ='ALLEGATO 1 CONDOMINI'!E40 -> 0 | U25: ='ALLEGATO 1 CONDOMINI'!F40 -> 0 | V25: ='ALLEGATO 1 CONDOMINI'!G40 -> 0 | AA25: RID | AB25: 30DF | AC25: COND | AD25: NO | AE25: ND | AJ25: =D25 -> #REF! | AL25: CLIENTI | AM25: 22 | AN25: 5 | AO25: 2 | AP25: 9904 | AS25: COND.USO DOM LIBERO | AU25: SWITCH | AV25: C1 | AW25: 1 | AX25: 00001 | AY25: =MID(BN25,1,4) -> 0 | BB25: 12 | BC25: =IF(BD25<=4999,"04","12") -> 04 | BD25: ='ALLEGATO 1 CONDOMINI'!P40 -> 0 | BK25: RID | BL25: 30DF | BM25: ND | BN25: ='ALLEGATO 1 CONDOMINI'!L40 -> 0 | BO25: ='ALLEGATO 1 CONDOMINI'!O40 -> 0 | BU25: =T25 -> 0 | BV25: =U25 -> 0 | BW25: =V25 -> 0 | CB25: ='ALLEGATO 1 CONDOMINI'!N40 -> 0 | CQ25: AMMINISTRATORE | DE25: ATTIVA | DG25: =AF25 -> 0 | DH25: =AG25 -> 0 | DI25: ='ALLEGATO 1 CONDOMINI'!K40 -> 0 | DJ25: B5746 | ED25: =VLOOKUP('[1]ALLEGATO 1 CONDOMINI'!K40,[1]Venditori!B:E,4,FALSE) -> #REF! | EI25: G | EK25: profilo di prelievo | EL25: COND | EO25: =MID(D25,1,20) -> #REF! | ER25: Controparte Commerciale & UDD | EV25: Core | FT25: 97.00.02 | GJ25: NO | GK25: NO | GL25: NO | GN25: 28 | GO25: NO | GP25: ITA
A33: CELLA BIANCA | B33: Formule
A34: CELLA GIALLA | B34: Cella da bloccare
A35: CELLA VERDE | B35: Modifica manuale
A36: CELLA BLU | B36: Celle vuote no dato

Sheet Template EE
A1: Cliente Numero | B1: Cliente - Nome | C1: Cliente - Cognome | D1: Cliente - Ragione Sociale | E1: Cliente - Partita IVA | F1: Cliente - Codice Fiscale | G1: Cliente - Telefono | H1: Cliente - Fax | I1: Cliente - E-Mail | J1: Cliente - E-Mail PEC | K1: Cliente - Cat. Reg. Business | L1: Cliente - Cat. Reg. Business IVA | M1: Cliente - Cat. Reg. Cliente | N1: Cliente - Cod. Agente | O1: Cliente - Nome Agente | P1: Indirizzo Cliente - Cod. Zona | Q1: Indirizzo Cliente - Desc. Comune | R1: Indirizzo Cliente - CAP | S1: Indirizzo Cliente - Cod. Provincia | T1: Indirizzo Cliente - Tipo Via | U1: Indirizzo Cliente - Nome Via | V1: Indirizzo Cliente - Civico | W1: Indirizzo Cliente - Estensione | X1: Indirizzo Cliente - Scala | Y1: Indirizzo Cliente - Piano | Z1: Indirizzo Cliente - Interno | AA1: Cliente - Codice Metodo Di Pagamento | AB1: Cliente - Codice Condizioni Di Pagamento | AC1: Cliente - Codice Termini di Sollecito | AD1: Cliente - Esente Mora | AE1: Rappresentante Legale - Nome | AF1: Rappresentante Legale - Cod. Fiscale | AG1: Utenza - Nome | AH1: Utenza - Cognome | AI1: Utenza - Ragione Sociale | AJ1: Utenza - Cod. Raggruppamento | AK1: Utenza - Cat. Reg. Business | AL1: Utenza - Cat. Reg. Business IVA | AM1: Utenza - Tipo Utenza | AN1: Utenza - Classe Utenza | AO1: Utenza - Categoria Utenza | AP1: Utenza - Cod. Agente | AQ1: Utenza - Nome Agente | AR1: Utenza - Tipo Mercato | AS1: Utenza - Tipo Mercato Di Provenienza | AT1: Utenza - Provenienza Prenotazione | AU1: Utenza - Cod. Venditore | AV1: Utenza - Cod. Distributore | AW1: Utenza - Cod. Fornitore | AX1: Utenza - Data Apertura | AY1: Utenza - Frequenza Fatturazione | AZ1: Utenza - Consumo Annuo Presunto KWH | BA1: Utenza - Tipologia Offerta | BB1: Utenza - Cod. Offerta | BC1: Utenza - Data Inizio Offerta | BD1: Utenza - Data Fine Offerta | BE1: Utenza - Tipo Invio Fatture | BF1: Utenza - Codice Metodo Di Pagamento | BG1: Utenza - Codice Condizioni Di Pagamento | BH1: Utenza - Tipo Configurazione Mora | BI1: Utenza - Potenza Disponibile (kW) | BJ1: Utenza - Potenza Impegnata (kW) | BK1: Utenza - Tensione Nominale (V) | BL1: Utenza - Livello di Tensione | BM1: Utenza - Fasce Orarie di Fatturazione | BN1: POD - Nr. | BO1: POD - Cod. Zona (ISTAT) | BP1: POD - Città | BQ1: POD - CAP | BR1: POD - Cod. Provincia | BS1: POD - Tipo Via | BT1: POD - Nome Via | BU1: POD - Civico | BV1: POD - Estensione | BW1: Punto di Riconsegna - Scala | BX1: Punto di Riconsegna - Piano | BY1: POD - Interno | BZ1: Contratto - Nr. | CA1: Contratto - Data Apertura | CB1: Contratto - Data Scadenza | CC1: Corrispondenza - Tipo | CD1: Corrispondenza - Nome | CE1: Corrispondenza - E-Mail | CF1: Corrispondenza - Cod. Zona | CG1: Corrispondenza - Città | CH1: Corrispondenza - CAP | CI1: Corrispondenza - Provincia | CJ1: Corrispondenza - Tipo Via | CK1: Corrispondenza - Nome Via | CL1: Corrispondenza - Numero Civico | CM1: Corrispondenza - Estensione Civico | CN1: Corrispondenza - Scala | CO1: Corrispondenza - Piano | CP1: Corrispondenza - Interno | CQ1: Domiciliazione - Stato | CR1: Domiciliazione - Cod. Domiciliazione | CS1: Domiciliazione - Nome Intestatario | CT1: Domiciliazione - Codice Fiscale Intestatario | CU1: Domiciliazione - IBAN | CV1: Domiciliazione - Cod. SIA | CW1: Domiciliazione - Data Inizio Domiciliazione | CX1: Domiciliazione - Data Inizio Garanzie | CY1: Domiciliazione - Tipo Partner | CZ1: Lettera Intento - Nr. | DA1: Lettera Intento - Decorrenza Da | DB1: Lettera Intento - Decorrenza A | DC1: Dati Catastali - Cod. Comune | DD1: Dati Catastali - Foglio | DE1: Dati Catastali - Tavola | DF1: Dati Catastali - Particella | DG1: Dati Catastali - Subalterno | DH1: Cod. Stampa | DI1: Tipo UDD | DJ1: Cod. Venditore Precedente | DK1: Utenza - Nr. | DL1: Utenza - Nr. Amministratore | DM1: Amministratore - Nome | DN1: Amministratore - Cognome | DO1: Amministratore - Ragione Sociale | DP1: Amministratore - Codice Fiscale | DQ1: Amministratore - Paritita IVA | DR1: Amministratore - Cod. Zona (ISTAT) | DS1: Amministratore - Città | DT1: Amministratore - CAP | DU1: Amministratore - Cod. Provincia | DV1: Amministratore - Tipo Via | DW1: Amministratore - Nome Via | DX1: Amministratore - Civico | DY1: Amministratore - Estensione | DZ1: Amministratore - Scala | EA1: Amministratore - Piano | EB1: Amministratore - Interno | EC1: Amministratore - Telefono | ED1: Amministratore - E-Mail | EE1: Contratto - Data firma contratto | EF1: Tipo Contratto | EG1: Utenza - Data Switch Vendita | EH1: Utenza - Cod. Termini di Sollecito | EI1: Utenza - Cod. Settore Merceologico | EJ1: Utenza - Campo Personalizzato 1 | EK1: Utenza - Campo Personalizzato 2 | EL1: Utenza - Campo Personalizzato 3 | EM1: Utenza - Nr. Contratto Esterno | EN1: Utenza - Cod. Accisa Personale | EO1: Dichiarazione Intento - Anno Dichiarazione | EP1: Dichiarazione Intento - Plafond Iniziale | EQ1: Dichiarazione Intento - Data Presentazione Dichiarazione | ER1: Dichiarazione Intento - Nr. Attribuito dal Dichiarante | ES1: Dichiarazione Intento - Anno Attribuito dal Dichiarante | ET1: Dichiarazione Intento - Nr. Attribuito dal Fornitore | EU1: Dichiarazione Intento - Anno Attribuito dal Fornitore | EV1: Consenso Future iniziative promozionali curate dalla società di vendita | EW1: Consenso Future iniziative promozionali curate da altre imprese del settore energia e servizi | EX1: Analisi/ricerche di mercato effettuate direttamente dalla società di vendita tramite società terze | EY1: Codice OU | EZ1: Cliente - Autorizzazione Invio SMS | FA1: Cliente - Tipo Telefono | FB1: Cliente - Codice Lingua | FC1: Utenza - Layout Stampa | FD1: Utenza - Nome controparte | FE1: Utenza - Cognome controparte | FF1: Utenza - Nome completo controparte | FG1: Utenza - Partita Iva controparte | FH1: Utenza - Codice Fiscale controparte | FI1: Nr. contratto PA | FJ1: Codice CIG | FK1: Codice CUP | FL1: Contratto - Luogo Firma Contratto
D2: =_xlfn.CONCAT('ALLEGATO 1 CONDOMINI'!B56,'ALLEGATO 1 CONDOMINI'!C56) -> COND. | F2: ='ALLEGATO 1 CONDOMINI'!D56 -> 0 | K2: CLIENTI | L2: ='ALLEGATO 1 CONDOMINI'!P56 -> 0 | M2: CLI-RD | P2: =VLOOKUP(Q2,'Zone Istat'!A:B,2,FALSE) -> #N/A | Q2: ='ALLEGATO 1 CONDOMINI'!I56 -> 0 | R2: =VLOOKUP(Q2,'Zone Istat'!A:E,5,FALSE) -> #N/A | S2: =VLOOKUP(Q2,'Zone Istat'!A:D,4,FALSE) -> #N/A | T2: ='ALLEGATO 1 CONDOMINI'!E56 -> 0 | U2: ='ALLEGATO 1 CONDOMINI'!F56 -> 0 | V2: ='ALLEGATO 1 CONDOMINI'!G56 -> 0 | AA2: RID | AB2: 30DF | AC2: COND | AD2: NO | AI2: =D2 -> COND. | AK2: CLIENTI | AL2: ='ALLEGATO 1 CONDOMINI'!P56 -> 0 | AM2: CONDOMINI | AO2: 9904 | AR2: COND.LIBERO | AS2: LIBERO | AT2: SWITCH | AU2: 00001 | AV2: =MID(BN2,3,4) | AY2: 12 | AZ2: ='ALLEGATO 1 CONDOMINI'!O56 -> 0 | BF2: RID | BG2: 30DF | BH2: ND | BI2: ='ALLEGATO 1 CONDOMINI'!Q56 -> 0 | BJ2: ='ALLEGATO 1 CONDOMINI'!R56 -> 0 | BK2: ='ALLEGATO 1 CONDOMINI'!S56 -> 0 | BL2: BT | BM2: MULTI | BN2: ='ALLEGATO 1 CONDOMINI'!L56 -> 0 | BO2: =P2 -> #N/A | BP2: =Q2 -> 0 | BQ2: =R2 -> #N/A | BR2: =S2 -> #N/A | BS2: ='ALLEGATO 1 CONDOMINI'!E56 -> 0 | BT2: ='ALLEGATO 1 CONDOMINI'!F56 -> 0 | BU2: ='ALLEGATO 1 CONDOMINI'!G56 -> 0 | CC2: AMMINISTRATORE | CQ2: ATTIVA | CS2: =AE2 -> 0 | CT2: =AF2 -> 0 | CU2: ='ALLEGATO 1 CONDOMINI'!K56 -> 0 | CV2: B5746 | DI2: Controparte Commerciale | DJ2: =VLOOKUP('ALLEGATO 1 CONDOMINI'!N56,Venditori!B:E,4,FALSE) -> #N/A | EH2: COND | EI2: 97.00.02 | EJ2: =MID(D2,1,20) -> COND. | EV2: 1 | EW2: 1 | EX2: 1 | FB2: ITA
D3: =_xlfn.CONCAT('ALLEGATO 1 CONDOMINI'!B57,'ALLEGATO 1 CONDOMINI'!C57) -> COND. | F3: ='ALLEGATO 1 CONDOMINI'!D57 -> 0 | K3: CLIENTI | L3: ='ALLEGATO 1 CONDOMINI'!P57 -> 0 | M3: CLI-RD | P3: =VLOOKUP(Q3,'Zone Istat'!A:B,2,FALSE) -> #N/A | Q3: ='ALLEGATO 1 CONDOMINI'!I57 -> 0 | R3: =VLOOKUP(Q3,'Zone Istat'!A:E,5,FALSE) -> #N/A | S3: =VLOOKUP(Q3,'Zone Istat'!A:D,4,FALSE) -> #N/A | T3: ='ALLEGATO 1 CONDOMINI'!E57 -> 0 | U3: ='ALLEGATO 1 CONDOMINI'!F57 -> 0 | V3: ='ALLEGATO 1 CONDOMINI'!G57 -> 0 | AA3: RID | AB3: 30DF | AC3: COND | AD3: NO | AI3: =D3 -> COND. | AK3: CLIENTI | AL3: ='ALLEGATO 1 CONDOMINI'!P57 -> 0 | AM3: CONDOMINI | AO3: 9904 | AR3: COND.LIBERO | AS3: LIBERO | AT3: SWITCH | AU3: 00001 | AV3: =MID(BN3,3,4) | AY3: 12 | AZ3: ='ALLEGATO 1 CONDOMINI'!O57 -> 0 | BF3: RID | BG3: 30DF | BH3: ND | BI3: ='ALLEGATO 1 CONDOMINI'!Q57 -> 0 | BJ3: ='ALLEGATO 1 CONDOMINI'!R57 -> 0 | BK3: ='ALLEGATO 1 CONDOMINI'!S57 -> 0 | BL3: BT | BM3: MULTI | BN3: ='ALLEGATO 1 CONDOMINI'!L57 -> 0 | BO3: =P3 -> #N/A | BP3: =Q3 -> 0 | BQ3: =R3 -> #N/A | BR3: =S3 -> #N/A | BS3: ='ALLEGATO 1 CONDOMINI'!E57 -> 0 | BT3: ='ALLEGATO 1 CONDOMINI'!F57 -> 0 | BU3: ='ALLEGATO 1 CONDOMINI'!G57 -> 0 | CC3: AMMINISTRATORE | CQ3: ATTIVA | CS3: =AE3 -> 0 | CT3: =AF3 -> 0 | CU3: ='ALLEGATO 1 CONDOMINI'!K57 -> 0 | CV3: B5746 | DI3: Controparte Commerciale | DJ3: =VLOOKUP('ALLEGATO 1 CONDOMINI'!N57,Venditori!B:E,4,FALSE) -> #N/A | EH3: COND | EI3: 97.00.02 | EJ3: =MID(D3,1,20) -> COND. | EV3: 1 | EW3: 1 | EX3: 1 | FB3: ITA
D4: =_xlfn.CONCAT('ALLEGATO 1 CONDOMINI'!B58,'ALLEGATO 1 CONDOMINI'!C58) -> COND. | F4: ='ALLEGATO 1 CONDOMINI'!D58 -> 0 | K4: CLIENTI | L4: ='ALLEGATO 1 CONDOMINI'!P58 -> 0 | M4: CLI-RD | P4: =VLOOKUP(Q4,'Zone Istat'!A:B,2,FALSE) -> #N/A | Q4: ='ALLEGATO 1 CONDOMINI'!I58 -> 0 | R4: =VLOOKUP(Q4,'Zone Istat'!A:E,5,FALSE) -> #N/A | S4: =VLOOKUP(Q4,'Zone Istat'!A:D,4,FALSE) -> #N/A | T4: ='ALLEGATO 1 CONDOMINI'!E58 -> 0 | U4: ='ALLEGATO 1 CONDOMINI'!F58 -> 0 | V4: ='ALLEGATO 1 CONDOMINI'!G58 -> 0 | AA4: RID | AB4: 30DF | AC4: COND | AD4: NO | AI4: =D4 -> COND. | AK4: CLIENTI | AL4: ='ALLEGATO 1 CONDOMINI'!P58 -> 0 | AM4: CONDOMINI | AO4: 9904 | AR4: COND.LIBERO | AS4: LIBERO | AT4: SWITCH | AU4: 00001 | AV4: =MID(BN4,3,4) | AY4: 12 | AZ4: ='ALLEGATO 1 CONDOMINI'!O58 -> 0 | BF4: RID | BG4: 30DF | BH4: ND | BI4: ='ALLEGATO 1 CONDOMINI'!Q58 -> 0 | BJ4: ='ALLEGATO 1 CONDOMINI'!R58 -> 0 | BK4: ='ALLEGATO 1 CONDOMINI'!S58 -> 0 | BL4: BT | BM4: MULTI | BN4: ='ALLEGATO 1 CONDOMINI'!L58 -> 0 | BO4: =P4 -> #N/A | BP4: =Q4 -> 0 | BQ4: =R4 -> #N/A | BR4: =S4 -> #N/A | BS4: ='ALLEGATO 1 CONDOMINI'!E58 -> 0 | BT4: ='ALLEGATO 1 CONDOMINI'!F58 -> 0 | BU4: ='ALLEGATO 1 CONDOMINI'!G58 -> 0 | CC4: AMMINISTRATORE | CQ4: ATTIVA | CS4: =AE4 -> 0 | CT4: =AF4 -> 0 | CU4: ='ALLEGATO 1 CONDOMINI'!K58 -> 0 | CV4: B5746 | DI4: Controparte Commerciale | DJ4: =VLOOKUP('ALLEGATO 1 CONDOMINI'!N58,Venditori!B:E,4,FALSE) -> #N/A | EH4: COND | EI4: 97.00.02 | EJ4: =MID(D4,1,20) -> COND. | EV4: 1 | EW4: 1 | EX4: 1 | FB4: ITA
D5: =_xlfn.CONCAT('ALLEGATO 1 CONDOMINI'!B59,'ALLEGATO 1 CONDOMINI'!C59) -> COND. | F5: ='ALLEGATO 1 CONDOMINI'!D59 -> 0 | K5: CLIENTI | L5: ='ALLEGATO 1 CONDOMINI'!P59 -> 0 | M5: CLI-RD | P5: =VLOOKUP(Q5,'Zone Istat'!A:B,2,FALSE) -> #N/A | Q5: ='ALLEGATO 1 CONDOMINI'!I59 -> 0 | R5: =VLOOKUP(Q5,'Zone Istat'!A:E,5,FALSE) -> #N/A | S5: =VLOOKUP(Q5,'Zone Istat'!A:D,4,FALSE) -> #N/A | T5: ='ALLEGATO 1 CONDOMINI'!E59 -> 0 | U5: ='ALLEGATO 1 CONDOMINI'!F59 -> 0 | V5: ='ALLEGATO 1 CONDOMINI'!G59 -> 0 | W5: SNC | AA5: RID | AB5: 30DF | AC5: COND | AD5: NO | AI5: =D5 -> COND. | AK5: CLIENTI | AL5: ='ALLEGATO 1 CONDOMINI'!P59 -> 0 | AM5: CONDOMINI | AO5: 9904 | AR5: COND.LIBERO | AS5: LIBERO | AT5: SWITCH | AU5: 00001 | AV5: =MID(BN5,3,4) | AY5: 12 | AZ5: ='ALLEGATO 1 CONDOMINI'!O59 -> 0 | BF5: RID | BG5: 30DF | BH5: ND | BI5: ='ALLEGATO 1 CONDOMINI'!Q59 -> 0 | BJ5: ='ALLEGATO 1 CONDOMINI'!R59 -> 0 | BK5: ='ALLEGATO 1 CONDOMINI'!S59 -> 0 | BL5: BT | BM5: MULTI | BN5: ='ALLEGATO 1 CONDOMINI'!L59 -> 0 | BO5: =P5 -> #N/A | BP5: =Q5 -> 0 | BQ5: =R5 -> #N/A | BR5: =S5 -> #N/A | BS5: ='ALLEGATO 1 CONDOMINI'!E59 -> 0 | BT5: ='ALLEGATO 1 CONDOMINI'!F59 -> 0 | BV5: SNC | CC5: AMMINISTRATORE | CQ5: ATTIVA | CS5: =AE5 -> 0 | CT5: =AF5 -> 0 | CU5: ='ALLEGATO 1 CONDOMINI'!K59 -> 0 | CV5: B5746 | DI5: Controparte Commerciale | DJ5: =VLOOKUP('ALLEGATO 1 CONDOMINI'!N59,Venditori!B:E,4,FALSE) -> #N/A | EH5: COND | EI5: 97.00.02 | EJ5: =MID(D5,1,20) -> COND. | EV5: 1 | EW5: 1 | EX5: 1 | FB5: ITA
D6: =_xlfn.CONCAT('ALLEGATO 1 CONDOMINI'!B60,'ALLEGATO 1 CONDOMINI'!C60) -> COND. | F6: ='ALLEGATO 1 CONDOMINI'!D60 -> 0 | K6: CLIENTI | L6: ='ALLEGATO 1 CONDOMINI'!P60 -> 0 | M6: CLI-RD | P6: =VLOOKUP(Q6,'Zone Istat'!A:B,2,FALSE) -> #N/A | Q6: ='ALLEGATO 1 CONDOMINI'!I60 -> 0 | R6: =VLOOKUP(Q6,'Zone Istat'!A:E,5,FALSE) -> #N/A | S6: =VLOOKUP(Q6,'Zone Istat'!A:D,4,FALSE) -> #N/A | T6: ='ALLEGATO 1 CONDOMINI'!E60 -> 0 | U6: ='ALLEGATO 1 CONDOMINI'!F60 -> 0 | V6: ='ALLEGATO 1 CONDOMINI'!G60 -> 0 | W6: SNC | AA6: RID | AB6: 30DF | AC6: COND | AD6: NO | AI6: =D6 -> COND. | AK6: CLIENTI | AL6: ='ALLEGATO 1 CONDOMINI'!P60 -> 0 | AM6: CONDOMINI | AO6: 9904 | AR6: COND.LIBERO | AS6: LIBERO | AT6: SWITCH | AU6: 00001 | AV6: =MID(BN6,3,4) | AY6: 12 | AZ6: ='ALLEGATO 1 CONDOMINI'!O60 -> 0 | BF6: RID | BG6: 30DF | BH6: ND | BI6: ='ALLEGATO 1 CONDOMINI'!Q60 -> 0 | BJ6: ='ALLEGATO 1 CONDOMINI'!R60 -> 0 | BK6: ='ALLEGATO 1 CONDOMINI'!S60 -> 0 | BL6: BT | BM6: MULTI | BN6: ='ALLEGATO 1 CONDOMINI'!L60 -> 0 | BO6: =P6 -> #N/A | BP6: =Q6 -> 0 | BQ6: =R6 -> #N/A | BR6: =S6 -> #N/A | BS6: ='ALLEGATO 1 CONDOMINI'!E60 -> 0 | BT6: ='ALLEGATO 1 CONDOMINI'!F60 -> 0 | BV6: SNC | CC6: AMMINISTRATORE | CQ6: ATTIVA | CS6: =AE6 -> 0 | CT6: =AF6 -> 0 | CU6: ='ALLEGATO 1 CONDOMINI'!K60 -> 0 | CV6: B5746 | DI6: Controparte Commerciale | DJ6: =VLOOKUP('ALLEGATO 1 CONDOMINI'!N60,Venditori!B:E,4,FALSE) -> #N/A | EH6: COND | EI6: 97.00.02 | EJ6: =MID(D6,1,20) -> COND. | EV6: 1 | EW6: 1 | EX6: 1 | FB6: ITA
D7: =_xlfn.CONCAT('ALLEGATO 1 CONDOMINI'!B61,'ALLEGATO 1 CONDOMINI'!C61) -> COND. | F7: ='ALLEGATO 1 CONDOMINI'!D61 -> 0 | K7: CLIENTI | L7: ='ALLEGATO 1 CONDOMINI'!P61 -> 0 | M7: CLI-RD | P7: =VLOOKUP(Q7,'Zone Istat'!A:B,2,FALSE) -> #N/A | Q7: ='ALLEGATO 1 CONDOMINI'!I61 -> 0 | R7: =VLOOKUP(Q7,'Zone Istat'!A:E,5,FALSE) -> #N/A | S7: =VLOOKUP(Q7,'Zone Istat'!A:D,4,FALSE) -> #N/A | T7: ='ALLEGATO 1 CONDOMINI'!E61 -> 0 | U7: ='ALLEGATO 1 CONDOMINI'!F61 -> 0 | V7: ='ALLEGATO 1 CONDOMINI'!G61 -> 0 | W7: SNC | AA7: RID | AB7: 30DF | AC7: COND | AD7: NO | AI7: =D7 -> COND. | AK7: CLIENTI | AL7: ='ALLEGATO 1 CONDOMINI'!P61 -> 0 | AM7: CONDOMINI | AO7: 9904 | AR7: COND.LIBERO | AS7: LIBERO | AT7: SWITCH | AU7: 00001 | AV7: =MID(BN7,3,4) | AY7: 12 | AZ7: ='ALLEGATO 1 CONDOMINI'!O61 -> 0 | BF7: RID | BG7: 30DF | BH7: ND | BI7: ='ALLEGATO 1 CONDOMINI'!Q61 -> 0 | BJ7: ='ALLEGATO 1 CONDOMINI'!R61 -> 0 | BK7: ='ALLEGATO 1 CONDOMINI'!S61 -> 0 | BL7: BT | BM7: MULTI | BN7: ='ALLEGATO 1 CONDOMINI'!L61 -> 0 | BO7: =P7 -> #N/A | BP7: =Q7 -> 0 | BQ7: =R7 -> #N/A | BR7: =S7 -> #N/A | BS7: ='ALLEGATO 1 CONDOMINI'!E61 -> 0 | BT7: ='ALLEGATO 1 CONDOMINI'!F61 -> 0 | BV7: SNC | CC7: AMMINISTRATORE | CQ7: ATTIVA | CS7: =AE7 -> 0 | CT7: =AF7 -> 0 | CU7: ='ALLEGATO 1 CONDOMINI'!K61 -> 0 | CV7: B5746 | DI7: Controparte Commerciale | DJ7: =VLOOKUP('ALLEGATO 1 CONDOMINI'!N61,Venditori!B:E,4,FALSE) -> #N/A | EH7: COND | EI7: 97.00.02 | EJ7: =MID(D7,1,20) -> COND. | EV7: 1 | EW7: 1 | EX7: 1 | FB7: ITA
D8: =_xlfn.CONCAT('ALLEGATO 1 CONDOMINI'!B62,'ALLEGATO 1 CONDOMINI'!C62) -> COND. | F8: ='ALLEGATO 1 CONDOMINI'!D62 -> 0 | K8: CLIENTI | L8: ='ALLEGATO 1 CONDOMINI'!P62 -> 0 | M8: CLI-RD | P8: =VLOOKUP(Q8,'Zone Istat'!A:B,2,FALSE) -> #N/A | Q8: ='ALLEGATO 1 CONDOMINI'!I62 -> 0 | R8: =VLOOKUP(Q8,'Zone Istat'!A:E,5,FALSE) -> #N/A | S8: =VLOOKUP(Q8,'Zone Istat'!A:D,4,FALSE) -> #N/A | T8: ='ALLEGATO 1 CONDOMINI'!E62 -> 0 | U8: ='ALLEGATO 1 CONDOMINI'!F62 -> 0 | V8: ='ALLEGATO 1 CONDOMINI'!G62 -> 0 | W8: SNC | AA8: RID | AB8: 30DF | AC8: COND | AD8: NO | AI8: =D8 -> COND. | AK8: CLIENTI | AL8: ='ALLEGATO 1 CONDOMINI'!P62 -> 0 | AM8: CONDOMINI | AO8: 9904 | AR8: COND.LIBERO | AS8: LIBERO | AT8: SWITCH | AU8: 00001 | AV8: =MID(BN8,3,4) | AY8: 12 | AZ8: ='ALLEGATO 1 CONDOMINI'!O62 -> 0 | BF8: RID | BG8: 30DF | BH8: ND | BI8: ='ALLEGATO 1 CONDOMINI'!Q62 -> 0 | BJ8: ='ALLEGATO 1 CONDOMINI'!R62 -> 0 | BK8: ='ALLEGATO 1 CONDOMINI'!S62 -> 0 | BL8: BT | BM8: MULTI | BN8: ='ALLEGATO 1 CONDOMINI'!L62 -> 0 | BO8: =P8 -> #N/A | BP8: =Q8 -> 0 | BQ8: =R8 -> #N/A | BR8: =S8 -> #N/A | BS8: ='ALLEGATO 1 CONDOMINI'!E62 -> 0 | BT8: ='ALLEGATO 1 CONDOMINI'!F62 -> 0 | BV8: SNC | CC8: AMMINISTRATORE | CQ8: ATTIVA | CS8: =AE8 -> 0 | CT8: =AF8 -> 0 | CU8: ='ALLEGATO 1 CONDOMINI'!K62 -> 0 | CV8: B5746 | DI8: Controparte Commerciale | DJ8: =VLOOKUP('ALLEGATO 1 CONDOMINI'!N62,Venditori!B:E,4,FALSE) -> #N/A | EH8: COND | EI8: 97.00.02 | EJ8: =MID(D8,1,20) -> COND. | EV8: 1 | EW8: 1 | EX8: 1 | FB8: ITA
D9: =_xlfn.CONCAT('ALLEGATO 1 CONDOMINI'!B63,'ALLEGATO 1 CONDOMINI'!C63) -> COND. | F9: ='ALLEGATO 1 CONDOMINI'!D63 -> 0 | K9: CLIENTI | L9: ='ALLEGATO 1 CONDOMINI'!P63 -> 0 | M9: CLI-RD | P9: =VLOOKUP(Q9,'Zone Istat'!A:B,2,FALSE) -> #N/A | Q9: ='ALLEGATO 1 CONDOMINI'!I63 -> 0 | R9: =VLOOKUP(Q9,'Zone Istat'!A:E,5,FALSE) -> #N/A | S9: =VLOOKUP(Q9,'Zone Istat'!A:D,4,FALSE) -> #N/A | T9: ='ALLEGATO 1 CONDOMINI'!E63 -> 0 | U9: ='ALLEGATO 1 CONDOMINI'!F63 -> 0 | V9: ='ALLEGATO 1 CONDOMINI'!G63 -> 0 | W9: SNC | AA9: RID | AB9: 30DF | AC9: COND | AD9: NO | AI9: =D9 -> COND. | AK9: CLIENTI | AL9: ='ALLEGATO 1 CONDOMINI'!P63 -> 0 | AM9: CONDOMINI | AO9: 9904 | AR9: COND.LIBERO | AS9: LIBERO | AT9: SWITCH | AU9: 00001 | AV9: =MID(BN9,3,4) | AY9: 12 | AZ9: ='ALLEGATO 1 CONDOMINI'!O63 -> 0 | BF9: RID | BG9: 30DF | BH9: ND | BI9: ='ALLEGATO 1 CONDOMINI'!Q63 -> 0 | BJ9: ='ALLEGATO 1 CONDOMINI'!R63 -> 0 | BK9: ='ALLEGATO 1 CONDOMINI'!S63 -> 0 | BL9: BT | BM9: MULTI | BN9: ='ALLEGATO 1 CONDOMINI'!L63 -> 0 | BO9: =P9 -> #N/A | BP9: =Q9 -> 0 | BQ9: =R9 -> #N/A | BR9: =S9 -> #N/A | BS9: ='ALLEGATO 1 CONDOMINI'!E63 -> 0 | BT9: ='ALLEGATO 1 CONDOMINI'!F63 -> 0 | BV9: SNC | CC9: AMMINISTRATORE | CQ9: ATTIVA | CS9: =AE9 -> 0 | CT9: =AF9 -> 0 | CU9: ='ALLEGATO 1 CONDOMINI'!K63 -> 0 | CV9: B5746 | DI9: Controparte Commerciale | DJ9: =VLOOKUP('ALLEGATO 1 CONDOMINI'!N63,Venditori!B:E,4,FALSE) -> #N/A | EH9: COND | EI9: 97.00.02 | EJ9: =MID(D9,1,20) -> COND. | EV9: 1 | EW9: 1 | EX9: 1 | FB9: ITA
D10: =_xlfn.CONCAT('ALLEGATO 1 CONDOMINI'!B64,'ALLEGATO 1 CONDOMINI'!C64) -> COND. | F10: ='ALLEGATO 1 CONDOMINI'!D64 -> 0 | K10: CLIENTI | L10: ='ALLEGATO 1 CONDOMINI'!P64 -> 0 | M10: CLI-RD | P10: =VLOOKUP(Q10,'Zone Istat'!A:B,2,FALSE) -> #N/A | Q10: ='ALLEGATO 1 CONDOMINI'!I64 -> 0 | R10: =VLOOKUP(Q10,'Zone Istat'!A:E,5,FALSE) -> #N/A | S10: =VLOOKUP(Q10,'Zone Istat'!A:D,4,FALSE) -> #N/A | T10: ='ALLEGATO 1 CONDOMINI'!E64 -> 0 | U10: ='ALLEGATO 1 CONDOMINI'!F64 -> 0 | V10: ='ALLEGATO 1 CONDOMINI'!G64 -> 0 | W10: SNC | AA10: RID | AB10: 30DF | AC10: COND | AD10: NO | AI10: =D10 -> COND. | AK10: CLIENTI | AL10: ='ALLEGATO 1 CONDOMINI'!P64 -> 0 | AM10: CONDOMINI | AO10: 9904 | AR10: COND.LIBERO | AS10: LIBERO | AT10: SWITCH | AU10: 00001 | AV10: =MID(BN10,3,4) | AY10: 12 | AZ10: ='ALLEGATO 1 CONDOMINI'!O64 -> 0 | BF10: RID | BG10: 30DF | BH10: ND | BI10: ='ALLEGATO 1 CONDOMINI'!Q64 -> 0 | BJ10: ='ALLEGATO 1 CONDOMINI'!R64 -> 0 | BK10: ='ALLEGATO 1 CONDOMINI'!S64 -> 0 | BL10: BT | BM10: MULTI | BN10: ='ALLEGATO 1 CONDOMINI'!L64 -> 0 | BO10: =P10 -> #N/A | BP10: =Q10 -> 0 | BQ10: =R10 -> #N/A | BR10: =S10 -> #N/A | BS10: ='ALLEGATO 1 CONDOMINI'!E64 -> 0 | BT10: ='ALLEGATO 1 CONDOMINI'!F64 -> 0 | BV10: SNC | CC10: AMMINISTRATORE | CQ10: ATTIVA | CS10: =AE10 -> 0 | CT10: =AF10 -> 0 | CU10: ='ALLEGATO 1 CONDOMINI'!K64 -> 0 | CV10: B5746 | DI10: Controparte Commerciale | DJ10: =VLOOKUP('ALLEGATO 1 CONDOMINI'!N64,Venditori!B:E,4,FALSE) -> #N/A | EH10: COND | EI10: 97.00.02 | EJ10: =MID(D10,1,20) -> COND. | EV10: 1 | EW10: 1 | EX10: 1 | FB10: ITA
D11: =_xlfn.CONCAT('ALLEGATO 1 CONDOMINI'!B65,'ALLEGATO 1 CONDOMINI'!C65) -> COND. | F11: ='ALLEGATO 1 CONDOMINI'!D65 -> 0 | K11: CLIENTI | L11: ='ALLEGATO 1 CONDOMINI'!P65 -> 0 | M11: CLI-RD | P11: =VLOOKUP(Q11,'Zone Istat'!A:B,2,FALSE) -> #N/A | Q11: ='ALLEGATO 1 CONDOMINI'!I65 -> 0 | R11: =VLOOKUP(Q11,'Zone Istat'!A:E,5,FALSE) -> #N/A | S11: =VLOOKUP(Q11,'Zone Istat'!A:D,4,FALSE) -> #N/A | T11: ='ALLEGATO 1 CONDOMINI'!E65 -> 0 | U11: ='ALLEGATO 1 CONDOMINI'!F65 -> 0 | V11: ='ALLEGATO 1 CONDOMINI'!G65 -> 0 | W11: SNC | AA11: RID | AB11: 30DF | AC11: COND | AD11: NO | AI11: =D11 -> COND. | AK11: CLIENTI | AL11: ='ALLEGATO 1 CONDOMINI'!P65 -> 0 | AM11: CONDOMINI | AO11: 9904 | AR11: COND.LIBERO | AS11: LIBERO | AT11: SWITCH | AU11: 00001 | AV11: =MID(BN11,3,4) | AY11: 12 | AZ11: ='ALLEGATO 1 CONDOMINI'!O65 -> 0 | BF11: RID | BG11: 30DF | BH11: ND | BI11: ='ALLEGATO 1 CONDOMINI'!Q65 -> 0 | BJ11: ='ALLEGATO 1 CONDOMINI'!R65 -> 0 | BK11: ='ALLEGATO 1 CONDOMINI'!S65 -> 0 | BL11: BT | BM11: MULTI | BN11: ='ALLEGATO 1 CONDOMINI'!L65 -> 0 | BO11: =P11 -> #N/A | BP11: =Q11 -> 0 | BQ11: =R11 -> #N/A | BR11: =S11 -> #N/A | BS11: ='ALLEGATO 1 CONDOMINI'!E65 -> 0 | BT11: ='ALLEGATO 1 CONDOMINI'!F65 -> 0 | BV11: SNC | CC11: AMMINISTRATORE | CQ11: ATTIVA | CS11: =AE11 -> 0 | CT11: =AF11 -> 0 | CU11: ='ALLEGATO 1 CONDOMINI'!K65 -> 0 | CV11: B5746 | DI11: Controparte Commerciale | DJ11: =VLOOKUP('ALLEGATO 1 CONDOMINI'!N65,Venditori!B:E,4,FALSE) -> #N/A | EH11: COND | EI11: 97.00.02 | EJ11: =MID(D11,1,20) -> COND. | EV11: 1 | EW11: 1 | EX11: 1 | FB11: ITA
D12: =_xlfn.CONCAT('ALLEGATO 1 CONDOMINI'!B66,'ALLEGATO 1 CONDOMINI'!C66) -> COND. | F12: ='ALLEGATO 1 CONDOMINI'!D66 -> 0 | K12: CLIENTI | L12: ='ALLEGATO 1 CONDOMINI'!P66 -> 0 | M12: CLI-RD | P12: =VLOOKUP(Q12,'Zone Istat'!A:B,2,FALSE) -> #N/A | Q12: ='ALLEGATO 1 CONDOMINI'!I66 -> 0 | R12: =VLOOKUP(Q12,'Zone Istat'!A:E,5,FALSE) -> #N/A | S12: =VLOOKUP(Q12,'Zone Istat'!A:D,4,FALSE) -> #N/A | T12: ='ALLEGATO 1 CONDOMINI'!E66 -> 0 | U12: ='ALLEGATO 1 CONDOMINI'!F66 -> 0 | V12: ='ALLEGATO 1 CONDOMINI'!G66 -> 0 | W12: SNC | AA12: RID | AB12: 30DF | AC12: COND | AD12: NO | AI12: =D12 -> COND. | AK12: CLIENTI | AL12: ='ALLEGATO 1 CONDOMINI'!P66 -> 0 | AM12: CONDOMINI | AO12: 9904 | AR12: COND.LIBERO | AS12: LIBERO | AT12: SWITCH | AU12: 00001 | AV12: =MID(BN12,3,4) | AY12: 12 | AZ12: ='ALLEGATO 1 CONDOMINI'!O66 -> 0 | BF12: RID | BG12: 30DF | BH12: ND | BI12: ='ALLEGATO 1 CONDOMINI'!Q66 -> 0 | BJ12: ='ALLEGATO 1 CONDOMINI'!R66 -> 0 | BK12: ='ALLEGATO 1 CONDOMINI'!S66 -> 0 | BL12: BT | BM12: MULTI | BN12: ='ALLEGATO 1 CONDOMINI'!L66 -> 0 | BO12: =P12 -> #N/A | BP12: =Q12 -> 0 | BQ12: =R12 -> #N/A | BR12: =S12 -> #N/A | BS12: ='ALLEGATO 1 CONDOMINI'!E66 -> 0 | BT12: ='ALLEGATO 1 CONDOMINI'!F66 -> 0 | BV12: SNC | CC12: AMMINISTRATORE | CQ12: ATTIVA | CS12: =AE12 -> 0 | CT12: =AF12 -> 0 | CU12: ='ALLEGATO 1 CONDOMINI'!K66 -> 0 | CV12: B5746 | DI12: Controparte Commerciale | DJ12: =VLOOKUP('ALLEGATO 1 CONDOMINI'!N66,Venditori!B:E,4,FALSE) -> #N/A | EH12: COND | EI12: 97.00.02 | EJ12: =MID(D12,1,20) -> COND. | EV12: 1 | EW12: 1 | EX12: 1 | FB12: ITA
D13: =_xlfn.CONCAT('ALLEGATO 1 CONDOMINI'!B67,'ALLEGATO 1 CONDOMINI'!C67) -> COND. | F13: ='ALLEGATO 1 CONDOMINI'!D67 -> 0 | K13: CLIENTI | L13: ='ALLEGATO 1 CONDOMINI'!P67 -> 0 | M13: CLI-RD | P13: =VLOOKUP(Q13,'Zone Istat'!A:B,2,FALSE) -> #N/A | Q13: ='ALLEGATO 1 CONDOMINI'!I67 -> 0 | R13: =VLOOKUP(Q13,'Zone Istat'!A:E,5,FALSE) -> #N/A | S13: =VLOOKUP(Q13,'Zone Istat'!A:D,4,FALSE) -> #N/A | T13: ='ALLEGATO 1 CONDOMINI'!E67 -> 0 | U13: ='ALLEGATO 1 CONDOMINI'!F67 -> 0 | V13: ='ALLEGATO 1 CONDOMINI'!G67 -> 0 | W13: SNC | AA13: RID | AB13: 30DF | AC13: COND | AD13: NO | AI13: =D13 -> COND. | AK13: CLIENTI | AL13: ='ALLEGATO 1 CONDOMINI'!P67 -> 0 | AM13: CONDOMINI | AO13: 9904 | AR13: COND.LIBERO | AS13: LIBERO | AT13: SWITCH | AU13: 00001 | AV13: =MID(BN13,3,4) | AY13: 12 | AZ13: ='ALLEGATO 1 CONDOMINI'!O67 -> 0 | BF13: RID | BG13: 30DF | BH13: ND | BI13: ='ALLEGATO 1 CONDOMINI'!Q67 -> 0 | BJ13: ='ALLEGATO 1 CONDOMINI'!R67 -> 0 | BK13: ='ALLEGATO 1 CONDOMINI'!S67 -> 0 | BL13: BT | BM13: MULTI | BN13: ='ALLEGATO 1 CONDOMINI'!L67 -> 0 | BO13: =P13 -> #N/A | BP13: =Q13 -> 0 | BQ13: =R13 -> #N/A | BR13: =S13 -> #N/A | BS13: ='ALLEGATO 1 CONDOMINI'!E67 -> 0 | BT13: ='ALLEGATO 1 CONDOMINI'!F67 -> 0 | BV13: SNC | CC13: AMMINISTRATORE | CQ13: ATTIVA | CS13: =AE13 -> 0 | CT13: =AF13 -> 0 | CU13: ='ALLEGATO 1 CONDOMINI'!K67 -> 0 | CV13: B5746 | DI13: Controparte Commerciale | DJ13: =VLOOKUP('ALLEGATO 1 CONDOMINI'!N67,Venditori!B:E,4,FALSE) -> #N/A | EH13: COND | EI13: 97.00.02 | EJ13: =MID(D13,1,20) -> COND. | EV13: 1 | EW13: 1 | EX13: 1 | FB13: ITA
D14: =_xlfn.CONCAT('ALLEGATO 1 CONDOMINI'!B68,'ALLEGATO 1 CONDOMINI'!C68) -> COND. | F14: ='ALLEGATO 1 CONDOMINI'!D68 -> 0 | K14: CLIENTI | L14: ='ALLEGATO 1 CONDOMINI'!P68 -> 0 | M14: CLI-RD | P14: =VLOOKUP(Q14,'Zone Istat'!A:B,2,FALSE) -> #N/A | Q14: ='ALLEGATO 1 CONDOMINI'!I68 -> 0 | R14: =VLOOKUP(Q14,'Zone Istat'!A:E,5,FALSE) -> #N/A | S14: =VLOOKUP(Q14,'Zone Istat'!A:D,4,FALSE) -> #N/A | T14: ='ALLEGATO 1 CONDOMINI'!E68 -> 0 | U14: ='ALLEGATO 1 CONDOMINI'!F68 -> 0 | V14: ='ALLEGATO 1 CONDOMINI'!G68 -> 0 | W14: SNC | AA14: RID | AB14: 30DF | AC14: COND | AD14: NO | AI14: =D14 -> COND. | AK14: CLIENTI | AL14: ='ALLEGATO 1 CONDOMINI'!P68 -> 0 | AM14: CONDOMINI | AO14: 9904 | AR14: COND.LIBERO | AS14: LIBERO | AT14: SWITCH | AU14: 00001 | AV14: =MID(BN14,3,4) | AY14: 12 | AZ14: ='ALLEGATO 1 CONDOMINI'!O68 -> 0 | BF14: RID | BG14: 30DF | BH14: ND | BI14: ='ALLEGATO 1 CONDOMINI'!Q68 -> 0 | BJ14: ='ALLEGATO 1 CONDOMINI'!R68 -> 0 | BK14: ='ALLEGATO 1 CONDOMINI'!S68 -> 0 | BL14: BT | BM14: MULTI | BN14: ='ALLEGATO 1 CONDOMINI'!L68 -> 0 | BO14: =P14 -> #N/A | BP14: =Q14 -> 0 | BQ14: =R14 -> #N/A | BR14: =S14 -> #N/A | BS14: ='ALLEGATO 1 CONDOMINI'!E68 -> 0 | BT14: ='ALLEGATO 1 CONDOMINI'!F68 -> 0 | BV14: SNC | CC14: AMMINISTRATORE | CQ14: ATTIVA | CS14: =AE14 -> 0 | CT14: =AF14 -> 0 | CU14: ='ALLEGATO 1 CONDOMINI'!K68 -> 0 | CV14: B5746 | DI14: Controparte Commerciale | DJ14: =VLOOKUP('ALLEGATO 1 CONDOMINI'!N68,Venditori!B:E,4,FALSE) -> #N/A | EH14: COND | EI14: 97.00.02 | EJ14: =MID(D14,1,20) -> COND. | EV14: 1 | EW14: 1 | EX14: 1 | FB14: ITA
D15: =_xlfn.CONCAT('ALLEGATO 1 CONDOMINI'!B69,'ALLEGATO 1 CONDOMINI'!C69) -> COND. | F15: ='ALLEGATO 1 CONDOMINI'!D69 -> 0 | K15: CLIENTI | L15: ='ALLEGATO 1 CONDOMINI'!P69 -> 0 | M15: CLI-RD | P15: =VLOOKUP(Q15,'Zone Istat'!A:B,2,FALSE) -> #N/A | Q15: ='ALLEGATO 1 CONDOMINI'!I69 -> 0 | R15: =VLOOKUP(Q15,'Zone Istat'!A:E,5,FALSE) -> #N/A | S15: =VLOOKUP(Q15,'Zone Istat'!A:D,4,FALSE) -> #N/A | T15: ='ALLEGATO 1 CONDOMINI'!E69 -> 0 | U15: ='ALLEGATO 1 CONDOMINI'!F69 -> 0 | V15: ='ALLEGATO 1 CONDOMINI'!G69 -> 0 | W15: SNC | AA15: RID | AB15: 30DF | AC15: COND | AD15: NO | AI15: =D15 -> COND. | AK15: CLIENTI | AL15: ='ALLEGATO 1 CONDOMINI'!P69 -> 0 | AM15: CONDOMINI | AO15: 9904 | AR15: COND.LIBERO | AS15: LIBERO | AT15: SWITCH | AU15: 00001 | AV15: =MID(BN15,3,4) | AY15: 12 | AZ15: ='ALLEGATO 1 CONDOMINI'!O69 -> 0 | BF15: RID | BG15: 30DF | BH15: ND | BI15: ='ALLEGATO 1 CONDOMINI'!Q69 -> 0 | BJ15: ='ALLEGATO 1 CONDOMINI'!R69 -> 0 | BK15: ='ALLEGATO 1 CONDOMINI'!S69 -> 0 | BL15: BT | BM15: MULTI | BN15: ='ALLEGATO 1 CONDOMINI'!L69 -> 0 | BO15: =P15 -> #N/A | BP15: =Q15 -> 0 | BQ15: =R15 -> #N/A | BR15: =S15 -> #N/A | BS15: ='ALLEGATO 1 CONDOMINI'!E69 -> 0 | BT15: ='ALLEGATO 1 CONDOMINI'!F69 -> 0 | BV15: SNC | CC15: AMMINISTRATORE | CQ15: ATTIVA | CS15: =AE15 -> 0 | CT15: =AF15 -> 0 | CU15: ='ALLEGATO 1 CONDOMINI'!K69 -> 0 | CV15: B5746 | DI15: Controparte Commerciale | DJ15: =VLOOKUP('ALLEGATO 1 CONDOMINI'!N69,Venditori!B:E,4,FALSE) -> #N/A | EH15: COND | EI15: 97.00.02 | EJ15: =MID(D15,1,20) -> COND. | EV15: 1 | EW15: 1 | EX15: 1 | FB15: ITA
D16: =_xlfn.CONCAT('ALLEGATO 1 CONDOMINI'!B70,'ALLEGATO 1 CONDOMINI'!C70) -> COND. | F16: ='ALLEGATO 1 CONDOMINI'!D70 -> 0 | K16: CLIENTI | L16: ='ALLEGATO 1 CONDOMINI'!P70 -> 0 | M16: CLI-RD | P16: =VLOOKUP(Q16,'Zone Istat'!A:B,2,FALSE) -> #N/A | Q16: ='ALLEGATO 1 CONDOMINI'!I70 -> 0 | R16: =VLOOKUP(Q16,'Zone Istat'!A:E,5,FALSE) -> #N/A | S16: =VLOOKUP(Q16,'Zone Istat'!A:D,4,FALSE) -> #N/A | T16: ='ALLEGATO 1 CONDOMINI'!E70 -> 0 | U16: ='ALLEGATO 1 CONDOMINI'!F70 -> 0 | V16: ='ALLEGATO 1 CONDOMINI'!G70 -> 0 | W16: SNC | AA16: RID | AB16: 30DF | AC16: COND | AD16: NO | AI16: =D16 -> COND. | AK16: CLIENTI | AL16: ='ALLEGATO 1 CONDOMINI'!P70 -> 0 | AM16: CONDOMINI | AO16: 9904 | AR16: COND.LIBERO | AS16: LIBERO | AT16: SWITCH | AU16: 00001 | AV16: =MID(BN16,3,4) | AY16: 12 | AZ16: ='ALLEGATO 1 CONDOMINI'!O70 -> 0 | BF16: RID | BG16: 30DF | BH16: ND | BI16: ='ALLEGATO 1 CONDOMINI'!Q70 -> 0 | BJ16: ='ALLEGATO 1 CONDOMINI'!R70 -> 0 | BK16: ='ALLEGATO 1 CONDOMINI'!S70 -> 0 | BL16: BT | BM16: MULTI | BN16: ='ALLEGATO 1 CONDOMINI'!L70 -> 0 | BO16: =P16 -> #N/A | BP16: =Q16 -> 0 | BQ16: =R16 -> #N/A | BR16: =S16 -> #N/A | BS16: ='ALLEGATO 1 CONDOMINI'!E70 -> 0 | BT16: ='ALLEGATO 1 CONDOMINI'!F70 -> 0 | BV16: SNC | CC16: AMMINISTRATORE | CQ16: ATTIVA | CS16: =AE16 -> 0 | CT16: =AF16 -> 0 | CU16: ='ALLEGATO 1 CONDOMINI'!K70 -> 0 | CV16: B5746 | DI16: Controparte Commerciale | DJ16: =VLOOKUP('ALLEGATO 1 CONDOMINI'!N70,Venditori!B:E,4,FALSE) -> #N/A | EH16: COND | EI16: 97.00.02 | EJ16: =MID(D16,1,20) -> COND. | EV16: 1 | EW16: 1 | EX16: 1 | FB16: ITA
... D21: =_xlfn.CONCAT('ALLEGATO 1 CONDOMINI'!B75,'ALLEGATO 1 CONDOMINI'!C75) -> COND. | F21: ='ALLEGATO 1 CONDOMINI'!D75 -> 0 | K21: CLIENTI | L21: ='ALLEGATO 1 CONDOMINI'!P75 -> 0 | M21: CLI-RD | P21: =VLOOKUP(Q21,'Zone Istat'!A:B,2,FALSE) -> #N/A | Q21: ='ALLEGATO 1 CONDOMINI'!I75 -> 0 | R21: =VLOOKUP(Q21,'Zone Istat'!A:E,5,FALSE) -> #N/A | S21: =VLOOKUP(Q21,'Zone Istat'!A:D,4,FALSE) -> #N/A | T21: ='ALLEGATO 1 CONDOMINI'!E75 -> 0 | U21: ='ALLEGATO 1 CONDOMINI'!F75 -> 0 | V21: ='ALLEGATO 1 CONDOMINI'!G75 -> 0 | W21: SNC | AA21: RID | AB21: 30DF | AC21: COND | AD21: NO | AI21: =D21 -> COND. | AK21: CLIENTI | AL21: ='ALLEGATO 1 CONDOMINI'!P75 -> 0 | AM21: CONDOMINI | AO21: 9904 | AR21: COND.LIBERO | AS21: LIBERO | AT21: SWITCH | AU21: 00001 | AV21: =MID(BN21,3,4) | AY21: 12 | AZ21: ='ALLEGATO 1 CONDOMINI'!O75 -> 0 | BF21: RID | BG21: 30DF | BH21: ND | BI21: ='ALLEGATO 1 CONDOMINI'!Q75 -> 0 | BJ21: ='ALLEGATO 1 CONDOMINI'!R75 -> 0 | BK21: ='ALLEGATO 1 CONDOMINI'!S75 -> 0 | BL21: BT | BM21: MULTI | BN21: ='ALLEGATO 1 CONDOMINI'!L75 -> 0 | BO21: =P21 -> #N/A | BP21: =Q21 -> 0 | BQ21: =R21 -> #N/A | BR21: =S21 -> #N/A | BS21: ='ALLEGATO 1 CONDOMINI'!E75 -> 0 | BT21: ='ALLEGATO 1 CONDOMINI'!F75 -> 0 | BV21: SNC | CC21: AMMINISTRATORE | CQ21: ATTIVA | CS21: =AE21 -> 0 | CT21: =AF21 -> 0 | CU21: ='ALLEGATO 1 CONDOMINI'!K75 -> 0 | CV21: B5746 | DI21: Controparte Commerciale | DJ21: =VLOOKUP('ALLEGATO 1 CONDOMINI'!N75,Venditori!B:E,4,FALSE) -> #N/A | EH21: COND | EI21: 97.00.02 | EJ21: =MID(D21,1,20) -> COND. | EV21: 1 | EW21: 1 | EX21: 1 | FB21: ITA
D22: =_xlfn.CONCAT('ALLEGATO 1 CONDOMINI'!B76,'ALLEGATO 1 CONDOMINI'!C76) | F22: ='ALLEGATO 1 CONDOMINI'!D76 -> 0 | K22: CLIENTI | L22: ='ALLEGATO 1 CONDOMINI'!P76 -> 0 | M22: CLI-RD | P22: =VLOOKUP(Q22,'Zone Istat'!A:B,2,FALSE) -> #N/A | Q22: ='ALLEGATO 1 CONDOMINI'!I76 -> 0 | R22: =VLOOKUP(Q22,'Zone Istat'!A:E,5,FALSE) -> #N/A | S22: =VLOOKUP(Q22,'Zone Istat'!A:D,4,FALSE) -> #N/A | T22: ='ALLEGATO 1 CONDOMINI'!E76 -> 0 | U22: ='ALLEGATO 1 CONDOMINI'!F76 -> 0 | V22: ='ALLEGATO 1 CONDOMINI'!G76 -> 0 | W22: SNC | AA22: RID | AB22: 30DF | AC22: COND | AD22: NO | AI22: =D22 | AK22: CLIENTI | AL22: ='ALLEGATO 1 CONDOMINI'!P76 -> 0 | AM22: CONDOMINI | AO22: 9904 | AR22: COND.LIBERO | AS22: LIBERO | AT22: SWITCH | AU22: 00001 | AV22: =MID(BN22,3,4) | AY22: 12 | AZ22: ='ALLEGATO 1 CONDOMINI'!O76 -> 0 | BF22: RID | BG22: 30DF | BH22: ND | BI22: ='ALLEGATO 1 CONDOMINI'!Q76 -> 0 | BJ22: ='ALLEGATO 1 CONDOMINI'!R76 -> 0 | BK22: ='ALLEGATO 1 CONDOMINI'!S76 -> 0 | BL22: BT | BM22: MULTI | BN22: ='ALLEGATO 1 CONDOMINI'!L76 -> 0 | BO22: =P22 -> #N/A | BP22: =Q22 -> 0 | BQ22: =R22 -> #N/A | BR22: =S22 -> #N/A | BS22: ='ALLEGATO 1 CONDOMINI'!E76 -> 0 | BT22: ='ALLEGATO 1 CONDOMINI'!F76 -> 0 | BV22: SNC | CC22: AMMINISTRATORE | CQ22: ATTIVA | CS22: =AE22 -> 0 | CT22: =AF22 -> 0 | CU22: ='ALLEGATO 1 CONDOMINI'!K76 -> 0 | CV22: B5746 | CW22: 45139 | DI22: Controparte Commerciale | DJ22: =VLOOKUP('ALLEGATO 1 CONDOMINI'!N76,Venditori!B:E,4,FALSE) -> #N/A | EH22: COND | EI22: 97.00.02 | EJ22: =MID(D22,1,20) | EV22: 1 | EW22: 1 | EX22: 1 | FB22: ITA
D23: =_xlfn.CONCAT('ALLEGATO 1 CONDOMINI'!B77,'ALLEGATO 1 CONDOMINI'!C77) | F23: ='ALLEGATO 1 CONDOMINI'!D77 -> 0 | K23: CLIENTI | L23: ='ALLEGATO 1 CONDOMINI'!P77 -> 0 | M23: CLI-RD | P23: =VLOOKUP(Q23,'Zone Istat'!A:B,2,FALSE) -> #N/A | Q23: ='ALLEGATO 1 CONDOMINI'!I77 -> 0 | R23: =VLOOKUP(Q23,'Zone Istat'!A:E,5,FALSE) -> #N/A | S23: =VLOOKUP(Q23,'Zone Istat'!A:D,4,FALSE) -> #N/A | T23: ='ALLEGATO 1 CONDOMINI'!E77 -> 0 | U23: ='ALLEGATO 1 CONDOMINI'!F77 -> 0 | V23: ='ALLEGATO 1 CONDOMINI'!G77 -> 0 | W23: SNC | AA23: RID | AB23: 30DF | AC23: COND | AD23: NO | AI23: =D23 | AK23: CLIENTI | AL23: ='ALLEGATO 1 CONDOMINI'!P77 -> 0 | AM23: CONDOMINI | AN23: BTA2 | AO23: 9904 | AR23: COND.LIBERO | AS23: LIBERO | AT23: SWITCH | AU23: 00001 | AV23: =MID(BN23,3,4) | AY23: 12 | AZ23: ='ALLEGATO 1 CONDOMINI'!O77 -> 0 | BF23: RID | BG23: 30DF | BH23: ND | BI23: ='ALLEGATO 1 CONDOMINI'!Q77 -> 0 | BJ23: ='ALLEGATO 1 CONDOMINI'!R77 -> 0 | BK23: ='ALLEGATO 1 CONDOMINI'!S77 -> 0 | BL23: BT | BM23: MULTI | BN23: ='ALLEGATO 1 CONDOMINI'!L77 -> 0 | BO23: =P23 -> #N/A | BP23: =Q23 -> 0 | BQ23: =R23 -> #N/A | BR23: =S23 -> #N/A | BS23: ='ALLEGATO 1 CONDOMINI'!E77 -> 0 | BT23: ='ALLEGATO 1 CONDOMINI'!F77 -> 0 | BV23: SNC | CC23: AMMINISTRATORE | CQ23: ATTIVA | CS23: =AE23 -> 0 | CT23: =AF23 -> 0 | CU23: ='ALLEGATO 1 CONDOMINI'!K77 -> 0 | CV23: B5746 | CW23: 45139 | DI23: Controparte Commerciale | DJ23: =VLOOKUP('ALLEGATO 1 CONDOMINI'!N77,Venditori!B:E,4,FALSE) -> #N/A | EH23: COND | EI23: 97.00.02 | EJ23: =MID(D23,1,20) | EV23: 1 | EW23: 1 | EX23: 1 | FB23: ITA
A26: CELLA BIANCA | B26: Formule
A27: CELLA GIALLA | B27: Cella da bloccare
A28: CELLA VERDE | B28: Modifica manuale
A29: CELLA BLU | B29: Celle vuote no dato

Sheet Zone Istat
A1: Città | B1: Cod. | C1: Cod. Provincia | D1: Provincia | E1: CAP
A2: AGLIÈ | B2: 001001 | C2: TO | D2: TO | E2: 10011
A3: AIRASCA | B3: 001002 | C3: TO | D3: TO | E3: 10060
A4: ALA DI STURA | B4: 001003 | C4: TO | D4: TO | E4: 10070
A5: ALBIANO D'IVREA | B5: 001004 | C5: TO | D5: TO | E5: 10010
A6: ALMESE | B6: 001006 | C6: TO | D6: TO | E6: 10040
A7: ALPETTE | B7: 001007 | C7: TO | D7: TO | E7: 10080
A8: ALPIGNANO | B8: 001008 | C8: TO | D8: TO | E8: 10091
A9: ANDEZENO | B9: 001009 | C9: TO | D9: TO | E9: 10020
A10: ANDRATE | B10: 001010 | C10: TO | D10: TO | E10: 10010
A11: ANGROGNA | B11: 001011 | C11: TO | D11: TO | E11: 10060
A12: ARIGNANO | B12: 001012 | C12: TO | D12: TO | E12: 10020
... A48: CAMBIANO | B48: 001048 | C48: TO | D48: TO | E48: 10020
A49: CAMPIGLIONE FENILE | B49: 001049 | C49: TO | D49: #N/A | E49: #N/A
A50: CANDIA CANAVESE | B50: 001050 | C50: TO | D50: TO | E50: 10010
A51: CANDIOLO | B51: 001051 | C51: TO | D51: TO | E51: 10060
A52: CANISCHIO | B52: 001052 | C52: TO | D52: TO | E52: 10080
A53: CANTALUPA | B53: 001053 | C53: TO | D53: TO | E53: 10060
A54: CANTOIRA | B54: 001054 | C54: TO | D54: TO | E54: 10070
A55: CAPRIE | B55: 001055 | C55: TO | D55: TO | E55: 10040
A56: CARAVINO | B56: 001056 | C56: TO | D56: TO | E56: 10010
A57: CAREMA | B57: 001057 | C57: TO | D57: TO | E57: 10010
A58: CARIGNANO | B58: 001058 | C58: TO | D58: TO | E58: 10041
A59: CARMAGNOLA | B59: 001059 | C59: TO | D59: TO | E59: 10022
A60: CASALBORGONE | B60: 001060 | C60: TO | D60: TO | E60: 10020
A61: CASCINETTE D'IVREA | B61: 001061 | C61: TO | D61: TO | E61: 10010
... A310: VOLVERA | B310: 001315 | C310: TO | D310: TO | E310: 10040
A311: MAPPANO | B311: 001316 | C311: TO | D311: #N/A | E311: #N/A
A312: VAL DI CHY | B312: 001317 | C312: TO | D312: #N/A | E312: #N/A
A313: VALCHIUSA | B313: 001318 | C313: TO | D313: #N/A | E313: #N/A
A314: ALAGNA VALSESIA | B314: 002002 | C314: VC | D314: VC | E314: 13021
A315: ALBANO VERCELLESE | B315: 002003 | C315: VC | D315: VC | E315: 13030
A316: ALICE CASTELLO | B316: 002004 | C316: VC | D316: VC | E316: 13040
A317: ARBORIO | B317: 002006 | C317: VC | D317: VC | E317: 13031
A318: ASIGLIANO VERCELLESE | B318: 002007 | C318: VC | D318: VC | E318: 13032
A319: BALMUCCIA | B319: 002008 | C319: VC | D319: VC | E319: 13020
A320: BALOCCO | B320: 002009 | C320: VC | D320: VC | E320: 13040
A321: BIANZÈ | B321: 002011 | C321: VC | D321: VC | E321: 13041
A322: BOCCIOLETO | B322: 002014 | C322: VC | D322: VC | E322: 13022
A323: BORGO D'ALE | B323: 002015 | C323: VC | D323: VC | E323: 13040
A324: BORGOSESIA | B324: 002016 | C324: VC | D324: VC | E324: 13011
A325: BORGO VERCELLI | B325: 002017 | C325: VC | D325: VC | E325: 13012
... A393: VOCCA | B393: 002166 | C393: VC | D393: VC | E393: 13020
A394: ALTO SERMENZA | B394: 002170 | C394: VC | D394: #N/A | E394: #N/A
A395: CELLIO CON BREIA | B395: 002171 | C395: VC | D395: #N/A | E395: #N/A
A396: AGRATE CONTURBIA | B396: 003001 | C396: NO | D396: NO | E396: 28010
A397: AMENO | B397: 003002 | C397: NO | D397: NO | E397: 28010
A398: ARMENO | B398: 003006 | C398: NO | D398: NO | E398: 28011
A399: ARONA | B399: 003008 | C399: NO | D399: NO | E399: 28041
A400: BARENGO | B400: 003012 | C400: NO | D400: NO | E400: 28010
A401: BELLINZAGO NOVARESE | B401: 003016 | C401: NO | D401: NO | E401: 28043
A402: BIANDRATE | B402: 003018 | C402: NO | D402: NO | E402: 28061
A403: BOCA | B403: 003019 | C403: NO | D403: NO | E403: 28010
A404: BOGOGNO | B404: 003021 | C404: NO | D404: NO | E404: 28010
A405: BOLZANO NOVARESE | B405: 003022 | C405: NO | D405: NO | E405: 28010
A406: BORGOLAVEZZARO | B406: 003023 | C406: NO | D406: NO | E406: 28071
A407: BORGOMANERO | B407: 003024 | C407: NO | D407: NO | E407: 28021
... A481: VINZAGLIO | B481: 003164 | C481: NO | D481: NO | E481: 28060
A482: GATTICO-VERUNO | B482: 003166 | C482: NO | D482: #N/A | E482: #N/A
A483: ACCEGLIO | B483: 004001 | C483: CN | D483: CN | E483: 12021
A484: AISONE | B484: 004002 | C484: CN | D484: CN | E484: 12010
A485: ALBA | B485: 004003 | C485: CN | D485: CN | E485: 12051
A486: ALBARETTO DELLA TORRE | B486: 004004 | C486: CN | D486: CN | E486: 12050
A487: ALTO | B487: 004005 | C487: CN | D487: CN | E487: 12070
A488: ARGENTERA | B488: 004006 | C488: CN | D488: CN | E488: 12010
A489: ARGUELLO | B489: 004007 | C489: CN | D489: CN | E489: 12050
A490: BAGNASCO | B490: 004008 | C490: CN | D490: CN | E490: 12071
A491: BAGNOLO PIEMONTE | B491: 004009 | C491: CN | D491: CN | E491: 12031
A492: BALDISSERO D'ALBA | B492: 004010 | C492: CN | D492: CN | E492: 12040
A493: BARBARESCO | B493: 004011 | C493: CN | D493: CN | E493: 12050
A494: BARGE | B494: 004012 | C494: CN | D494: CN | E494: 12032
... A530: CASTELLETTO UZZONE | B530: 004050 | C530: CN | D530: CN | E530: 12070
A531: CASTELLINALDO D'ALBA | B531: 004051 | C531: CN | D531: #N/A | E531: #N/A
A532: CASTELLINO TANARO | B532: 004052 | C532: CN | D532: CN | E532: 12060
A533: CASTELMAGNO | B533: 004053 | C533: CN | D533: CN | E533: 12020
A534: CASTELNUOVO DI CEVA | B534: 004054 | C534: CN | D534: CN | E534: 12070
A535: CASTIGLIONE FALLETTO | B535: 004055 | C535: CN | D535: CN | E535: 12060
A536: CASTIGLIONE TINELLA | B536: 004056 | C536: CN | D536: CN | E536: 12053
A537: CASTINO | B537: 004057 | C537: CN | D537: CN | E537: 12050
A538: CAVALLERLEONE | B538: 004058 | C538: CN | D538: CN | E538: 12030
A539: CAVALLERMAGGIORE | B539: 004059 | C539: CN | D539: CN | E539: 12030
A540: CELLE DI MACRA | B540: 004060 | C540: CN | D540: CN | E540: 12020
A541: CENTALLO | B541: 004061 | C541: CN | D541: CN | E541: 12044
A542: CERESOLE ALBA | B542: 004062 | C542: CN | D542: CN | E542: 12040
A543: CERRETTO LANGHE | B543: 004063 | C543: CN | D543: CN | E543: 12050
... A889: CASSINELLE | B889: 006044 | C889: AL | D889: AL | E889: 15070
A890: CASTELLANIA COPPI | B890: 006045 | C890: AL | D890: #N/A | E890: #N/A
A891: CASTELLAR GUIDOBONO | B891: 006046 | C891: AL | D891: AL | E891: 15050
A892: CASTELLAZZO BORMIDA | B892: 006047 | C892: AL | D892: AL | E892: 15073
A893: CASTELLETTO D'ERRO | B893: 006048 | C893: AL | D893: AL | E893: 15010
A894: CASTELLETTO D'ORBA | B894: 006049 | C894: AL | D894: AL | E894: 15060
A895: CASTELLETTO MERLI | B895: 006050 | C895: AL | D895: AL | E895: 15020
A896: CASTELLETTO MONFERRATO | B896: 006051 | C896: AL | D896: AL | E896: 15040
A897: CASTELNUOVO BORMIDA | B897: 006052 | C897: AL | D897: AL | E897: 15017
A898: CASTELNUOVO SCRIVIA | B898: 006053 | C898: AL | D898: AL | E898: 15053
A899: CASTELSPINA | B899: 006054 | C899: AL | D899: AL | E899: 15070
A900: CAVATORE | B900: 006055 | C900: AL | D900: AL | E900: 15010
A901: CELLA MONTE | B901: 006056 | C901: AL | D901: AL | E901: 15034
A902: CERESETO | B902: 006057 | C902: AL | D902: AL | E902: 15020
... A919: FRUGAROLO | B919: 006075 | C919: AL | D919: AL | E919: 15065
...

Sheet Venditori
A1: Cod. | B1: Descrizione | C1: Partita Iva | D1: Nr. di Fax | E1: Cod. | F1: Nr. di Telefono | G1: Indirizzo | H1: Default
A2: 00001 | B2: CHIURLO S.r.l | E2: 00001 | G2: Non compilato | H2: FALSE
A3: 00002 | B3: Bluenergy Group | E3: 00002 | G3: Non compilato | H3: FALSE
A4: 00003 | B4: Enerxenia | E4: 00003 | G4: Non compilato | H4: FALSE
A5: 00004 | B5: Amga Energia e Servizi | E5: 00004 | G5: Non compilato | H5: FALSE
A6: 00005 | B6: Trenta S.p.A. | C6: 09533760964 | E6: 00005 | G6: Non compilato | H6: FALSE
A7: 00006 | B7: Estraenergie | E7: 00006 | G7: Non compilato | H7: FALSE
A8: 00007 | B8: EStenergy | E8: 00007 | G8: Non compilato | H8: FALSE
A9: 00008 | B9: Eni - Plenitude | E9: 00008 | G9: Non compilato | H9: FALSE
A10: 00009 | B10: Energrid | E10: 00009 | G10: Non compilato | H10: FALSE
A11: 00010 | B11: Enel Energia | E11: 00010 | G11: Non compilato | H11: FALSE
A12: 00011 | B12: Isogas-ESt Più | E12: 00011 | G12: Non compilato | H12: FALSE
A13: 00012 | B13: Europagas srl | E13: 00012 | G13: Non compilato | H13: FALSE
A14: 00013 | B14: Repower | E14: 00013 | G14: Non compilato | H14: FALSE
A15: 00014 | B15: Edison | E15: 00014 | G15: Non compilato | H15: FALSE
A16: 00015 | B16: Azienda Energia e Gas | E16: 00015 | G16: Non compilato | H16: FALSE
A17: 00016 | B17: Veritas Energia | E17: 00016 | G17: Non compilato | H17: FALSE
A18: 00017 | B18: Ascotrade spa | E18: 00017 | G18: Non compilato | H18: FALSE
... A21: 00020 | B21: BPP gas | E21: 00020 | G21: Non compilato | H21: FALSE
A22: 00021 | B22: GDF Suez | C22: 09515990969 | E22: 00021 | G22: Non compilato | H22: FALSE
A23: 00022 | B23: ArgosEnergia | E23: 00022 | G23: Non compilato | H23: FALSE
A24: 00023 | B24: Trenta SPA | E24: 00023 | G24: Non compilato | H24: FALSE
A25: 00024 | B25: Unogas | E25: 00024 | G25: Non compilato | H25: FALSE
A26: 00025 | B26: Illumia | C26: 01970140065 | E26: 00025 | F26: +390131283611 | G26: Non compilato | H26: FALSE
A27: 00026 | B27: Energetic Source | E27: 00026 | G27: Non compilato | H27: FALSE
A28: 00027 | B28: Flyenergia | C28: 01745520211 | E28: 00027 | G28: Non compilato | H28: FALSE
A29: 00028 | B29: Spigas | E29: 00028 | G29: Non compilato | H29: FALSE
A30: 00029 | B30: Linea Più | E30: 00029 | G30: Non compilato | H30: FALSE
A31: 00030 | B31: Acegas Aps Service | C31: 05044850823 | E31: 00030 | G31: Non compilato | H31: FALSE
A32: 00031 | B32: Agsm Energia | E32: 00031 | G32: Non compilato | H32: FALSE
A33: 00032 | B33: HeraComm | E33: 00032 | G33: Non compilato | H33: FALSE
A34: 00033 | B34: Enegan | E34: 00033 | G34: Non compilato | H34: FALSE
A35: 00034 | B35: E-on | E35: 00034 | G35: Non compilato | H35: FALSE
A36: 00035 | B36: GreenNetwork | E36: 00035 | G36: Non compilato | H36: FALSE
A37: 00036 | B37: LineaPiù | E37: 00036 | G37: Non compilato | H37: FALSE
A38: 00037 | B38: Veneto Gas&Power | E38: 00037 | G38: Non compilato | H38: FALSE
A39: 00038 | B39: Vivigas Spa | E39: 00038 | G39: Non compilato | H39: FALSE
A40: 00039 | B40: Axpo | E40: 00039 | G40: Non compilato | H40: FALSE
A41: 00040 | B41: Optima | E41: 00040 | G41: Non compilato | H41: FALSE
A42: 00041 | B42: GeoNordest | E42: 00041 | G42: Non compilato | H42: FALSE
A43: 00042 | B43: DueEnergie | E43: 00042 | G43: Non compilato | H43: FALSE
... A47: 00046 | B47: Engie | E47: 00046 | G47: Non compilato | H47: FALSE
A48: 00047 | B48: GasNatural | C48: 06170180019 | E48: 00047 | G48: Non compilato | H48: FALSE
A49: 00048 | B49: Geko | E49: 00048 | G49: Non compilato | H49: FALSE
A50: 00049 | B50: Simecom | E50: 00049 | G50: Non compilato | H50: FALSE
A51: 00050 | B51: Idroelettrica Valcanale | C51: 01141160992 | E51: 00050 | G51: Non compilato | H51: FALSE
A52: 00051 | B52: Goldenergy | E52: 00051 | G52: Non compilato | H52: FALSE
A53: 00052 | B53: Gala | E53: 00052 | G53: Non compilato | H53: FALSE
A54: 00053 | B54: Sorgenia | E54: 00053 | G54: Non compilato | H54: FALSE
A55: 00054 | B55: 3C | C55: 10991371005 | E55: 00054 | G55: Non compilato | H55: FALSE
A56: 00055 | B56: Compagnia Energetica Italiana | C56: 10991371005 | E56: 00055 | G56: Non compilato | H56: FALSE
A57: 00056 | B57: Cura Gas&Power | E57: 00056 | G57: Non compilato | H57: FALSE
A58: 00057 | B58: Utilità | E58: 00057 | G58: Non compilato | H58: FALSE
A59: 00058 | B59: Iren | E59: 00058 | G59: Non compilato | H59: FALSE
A60: 00059 | B60: Multiutility | E60: 00059 | G60: Non compilato | H60: FALSE
A61: 00060 | B61: Sky Gas&Power | E61: 00060 | G61: Non compilato | H61: FALSE
A62: 00061 | B62: AF Energie | E62: 00061 | G62: Non compilato | H62: FALSE
A63: 00062 | B63: Burgo Energia | E63: 00062 | G63: Non compilato | H63: FALSE
A64: 00063 | B64: Beetwin | E64: 00063 | G64: Non compilato | H64: FALSE
A65: 00064 | B65: EnergiaCorrente | E65: 00064 | G65: Non compilato | H65: FALSE
A66: 00065 | B66: Antas | E66: 00065 | G66: Non compilato | H66: FALSE
A67: 00066 | B67: RomaGas | C67: 00894461003 | E67: 00066 | G67: Non compilato | H67: FALSE
A68: 00067 | B68: SoEnergy | E68: 00067 | G68: Non compilato | H68: FALSE
A69: 00068 | B69: BlueMeta | E69: 00068 | G69: Non compilato | H69: FALSE
A70: 00069 | B70: Asm Energia | E70: 00069 | G70: Non compilato | H70: FALSE
A71: 00070 | B71: Luce e Gas Italia | E71: 00070 | G71: Non compilato | H71: FALSE
A72: 00071 | B72: Elettragas | E72: 00071 | G72: Non compilato | H72: FALSE
A73: 00072 | B73: Invent | C73: 08345840964 | E73: 00072 | G73: Non compilato | H73: FALSE
A74: 00073 | B74: Dolomiti Energia | C74: 01274390309 | E74: 00073 | G74: Non compilato | H74: TRUE
A75: 00074 | B75: AP Energia | C75: 09328470159 | E75: 00074 | G75: Non compilato | H75: FALSE
A76: 00075 | B76: Audax Energia | E76: 00075 | G76: Non compilato | H76: FALSE
A77: 00076 | B77: Ubroker | E77: 00076 | G77: Non compilato | H77: FALSE
A78: 00077 | B78: Utility 360 | E78: 00077 | G78: Non compilato | H78: FALSE
A79: 00078 | B79: Axopower | E79: 00078 | G79: Non compilato | H79: FALSE
A80: 00079 | B80: LionEnergy | E80: 00079 | G80: Non compilato | H80: FALSE
A81: 00080 | B81: Aemme Energie | E81: 00080 | G81: Non compilato | H81: FALSE
A82: 00081 | B82: Metanotre | E82: 00081 | G82: Non compilato | H82: FALSE
A83: 00082 | B83: Energie Diffuse | E83: 00082 | G83: Non compilato | H83: FALSE
A84: 00083 | B84: FVG Energia | E84: 00083 | G84: Non compilato | H84: FALSE
A85: 00084 | B85: X3Energy | E85: 00084 | G85: Non compilato | H85: FALSE
A86: 00085 | B86: ACEA Energia | E86: 00085 | G86: Non compilato | H86: FALSE
A87: 00086 | B87: Casapiùverde | E87: 00086 | G87: Non compilato | H87: FALSE
... A95: 00095 | B95: SIMP GAS | E95: 00095 | G95: Non compilato | H95: FALSE
A96: 00096 | B96: ANTENORE | C96: 03469240547 | E96: 00096 | G96: Non compilato | H96: FALSE
A97: 00097 | B97: UNI. CO. GE | E97: 00097 | G97: Non compilato | H97: FALSE
A98: 00098 | B98: METAENERGIA | E98: 00098 | G98: Non compilato | H98: FALSE
A99: 00099 | B99: LIBERO | E99: 00099 | G99: Non compilato | H99: FALSE
A100: 00100 | B100: SOCIETA' SERVIZI ENERGIA SRL | E100: 00100 | G100: Non compilato | H100: FALSE
A101: 00101 | B101: AUDAX ENERGIA | E101: 00101 | G101: Non compilato | H101: FALSE
A102: 00102 | B102: Evivaenergia | E102: 00102 | G102: Non compilato | H102: FALSE
A103: 00103 | B103: Energrid | E103: 00103 | G103: Non compilato | H103: FALSE
A104: 00104 | B104: Simecom | E104: 00104 | G104: Non compilato | H104: FALSE
A105: 00105 | B105: SUISSE | E105: 00105 | G105: Non compilato | H105: FALSE
A106: 00106 | B106: EDLO ENERGY SPA | C106: 02465700033 | E106: 00106 | G106: Non compilato | H106: FALSE
A107: 00107 | B107: Passuello | E107: 00107 | G107: Non compilato | H107: FALSE
A108: 00108 | B108: SINERGY | C108: 01335290323 | E108: 00108 | G108: Non compilato | H108: FALSE
A109: 00109 | B109: ENERGY ONLY | C109: 01788310769 | E109: 00109 | G109: Non compilato | H109: FALSE
A110: 00110 | B110: S4 | E110: 00110 | G110: Non compilato | H110: FALSE
A111: 00111 | B111: ENERGIA BASE TRIESTE | E111: 00111 | G111: Non compilato | H111: FALSE
A112: 00112 | B112: MIWA | E112: 00112 | G112: Non compilato | H112: FALSE
...

Sheet Menù a tendina
A1: IVA G | B1: IVA EE
A2: 10 | B2: 10
A3: IVA22 | B3: IVA22SP
A4: 22SP | B4: 22
A5: 22 | B5: IVA22
